{
	"json_type": "people_count",
	"branch_name": "teste",
	"host_name": "host_name",
	"mac_address_device": "dc:a6:32:6b:8e:7e",
	"mac_address_count": "0c:9d:92:8e:bf:f0",
	"video_name": "debugRasp_dca6326b8e7e_2021-02-11_14-26-55-134774",
	"width": 800,
	"height": 600,
	"person_id": 937,
	"timestamp_registered": 1613064487.351609,
	"exits": [
		{
			"exit_name": "saida_0",
			"activity": 0,
			"param_global": {
				"name": "saida_0",
				"position": [
					[
						0.15625,
						0.485
					],
					[
						0.63125,
						0.805
					]
				],
				"exit_type": 1,
				"mask": null,
				"count": 0,
				"capacity": 0,
				"count_in": 0,
				"count_out": 0,
				"count_unknown": 0
			}
		},
		{
			"exit_name": "saida_1",
			"activity": 0,
			"param_global": {
				"name": "saida_1",
				"position": [
					[
						0.15625,
						0.49
					],
					[
						0.63125,
						0.805
					]
				],
				"exit_type": 3,
				"mask": null,
				"count": 528,
				"capacity": 0,
				"count_in": 199,
				"count_out": 199,
				"count_unknown": 0
			}
		},
		{
			"exit_name": "saida_2",
			"activity": 0,
			"param_global": {
				"name": "saida_2",
				"position": [
					[
						0.15625,
						0.495
					],
					[
						0.63125,
						0.805
					]
				],
				"exit_type": 3,
				"mask": null,
				"count": 525,
				"capacity": -2,
				"count_in": 199,
				"count_out": 200,
				"count_unknown": 0
			}
		},
		{
			"exit_name": "saida_3",
			"activity": 0,
			"param_global": {
				"name": "saida_3",
				"position": [
					[
						0.15625,
						0.5
					],
					[
						0.63125,
						0.805
					]
				],
				"exit_type": 3,
				"mask": null,
				"count": 524,
				"capacity": 0,
				"count_in": 200,
				"count_out": 200,
				"count_unknown": 0
			}
		},
		{
			"exit_name": "saida_4",
			"activity": 0,
			"param_global": {
				"name": "saida_4",
				"position": [
					[
						0.15625,
						0.505
					],
					[
						0.63125,
						0.805
					]
				],
				"exit_type": 3,
				"mask": null,
				"count": 522,
				"capacity": -2,
				"count_in": 199,
				"count_out": 200,
				"count_unknown": 0
			}
		},
		{
			"exit_name": "saida_5",
			"activity": 0,
			"param_global": {
				"name": "saida_5",
				"position": [
					[
						0.15625,
						0.51
					],
					[
						0.63125,
						0.805
					]
				],
				"exit_type": 3,
				"mask": null,
				"count": 518,
				"capacity": 0,
				"count_in": 199,
				"count_out": 199,
				"count_unknown": 0
			}
		},
		{
			"exit_name": "saida_6",
			"activity": 0,
			"param_global": {
				"name": "saida_6",
				"position": [
					[
						0.15625,
						0.515
					],
					[
						0.63125,
						0.805
					]
				],
				"exit_type": 3,
				"mask": null,
				"count": 516,
				"capacity": -4,
				"count_in": 198,
				"count_out": 200,
				"count_unknown": 0
			}
		},
		{
			"exit_name": "saida_7",
			"activity": 0,
			"param_global": {
				"name": "saida_7",
				"position": [
					[
						0.15625,
						0.52
					],
					[
						0.63125,
						0.805
					]
				],
				"exit_type": 3,
				"mask": null,
				"count": 515,
				"capacity": 0,
				"count_in": 199,
				"count_out": 199,
				"count_unknown": 0
			}
		},
		{
			"exit_name": "saida_8",
			"activity": 0,
			"param_global": {
				"name": "saida_8",
				"position": [
					[
						0.15625,
						0.525
					],
					[
						0.63125,
						0.805
					]
				],
				"exit_type": 3,
				"mask": null,
				"count": 515,
				"capacity": -4,
				"count_in": 198,
				"count_out": 200,
				"count_unknown": 0
			}
		},
		{
			"exit_name": "saida_9",
			"activity": 0,
			"param_global": {
				"name": "saida_9",
				"position": [
					[
						0.15625,
						0.53
					],
					[
						0.63125,
						0.805
					]
				],
				"exit_type": 3,
				"mask": null,
				"count": 512,
				"capacity": -4,
				"count_in": 199,
				"count_out": 201,
				"count_unknown": 0
			}
		},
		{
			"exit_name": "saida_10",
			"activity": 0,
			"param_global": {
				"name": "saida_10",
				"position": [
					[
						0.15625,
						0.535
					],
					[
						0.63125,
						0.805
					]
				],
				"exit_type": 3,
				"mask": null,
				"count": 511,
				"capacity": 0,
				"count_in": 200,
				"count_out": 200,
				"count_unknown": 0
			}
		},
		{
			"exit_name": "saida_11",
			"activity": 0,
			"param_global": {
				"name": "saida_11",
				"position": [
					[
						0.15625,
						0.54
					],
					[
						0.63125,
						0.805
					]
				],
				"exit_type": 3,
				"mask": null,
				"count": 506,
				"capacity": 2,
				"count_in": 201,
				"count_out": 200,
				"count_unknown": 0
			}
		},
		{
			"exit_name": "saida_12",
			"activity": 0,
			"param_global": {
				"name": "saida_12",
				"position": [
					[
						0.15625,
						0.545
					],
					[
						0.63125,
						0.805
					]
				],
				"exit_type": 3,
				"mask": null,
				"count": 503,
				"capacity": 4,
				"count_in": 202,
				"count_out": 200,
				"count_unknown": 0
			}
		},
		{
			"exit_name": "saida_13",
			"activity": 0,
			"param_global": {
				"name": "saida_13",
				"position": [
					[
						0.15625,
						0.55
					],
					[
						0.63125,
						0.805
					]
				],
				"exit_type": 3,
				"mask": null,
				"count": 502,
				"capacity": 6,
				"count_in": 202,
				"count_out": 199,
				"count_unknown": 0
			}
		},
		{
			"exit_name": "saida_14",
			"activity": 0,
			"param_global": {
				"name": "saida_14",
				"position": [
					[
						0.15625,
						0.555
					],
					[
						0.63125,
						0.805
					]
				],
				"exit_type": 3,
				"mask": null,
				"count": 500,
				"capacity": 2,
				"count_in": 202,
				"count_out": 201,
				"count_unknown": 0
			}
		},
		{
			"exit_name": "saida_15",
			"activity": 0,
			"param_global": {
				"name": "saida_15",
				"position": [
					[
						0.15625,
						0.56
					],
					[
						0.63125,
						0.805
					]
				],
				"exit_type": 3,
				"mask": null,
				"count": 498,
				"capacity": -2,
				"count_in": 200,
				"count_out": 201,
				"count_unknown": 0
			}
		},
		{
			"exit_name": "saida_16",
			"activity": 0,
			"param_global": {
				"name": "saida_16",
				"position": [
					[
						0.15625,
						0.5650000000000001
					],
					[
						0.63125,
						0.805
					]
				],
				"exit_type": 3,
				"mask": null,
				"count": 496,
				"capacity": 6,
				"count_in": 202,
				"count_out": 199,
				"count_unknown": 0
			}
		},
		{
			"exit_name": "saida_17",
			"activity": 0,
			"param_global": {
				"name": "saida_17",
				"position": [
					[
						0.15625,
						0.5700000000000001
					],
					[
						0.63125,
						0.805
					]
				],
				"exit_type": 3,
				"mask": null,
				"count": 496,
				"capacity": 4,
				"count_in": 201,
				"count_out": 199,
				"count_unknown": 0
			}
		},
		{
			"exit_name": "saida_18",
			"activity": 0,
			"param_global": {
				"name": "saida_18",
				"position": [
					[
						0.15625,
						0.5750000000000001
					],
					[
						0.63125,
						0.805
					]
				],
				"exit_type": 3,
				"mask": null,
				"count": 495,
				"capacity": 4,
				"count_in": 201,
				"count_out": 199,
				"count_unknown": 0
			}
		},
		{
			"exit_name": "saida_19",
			"activity": 0,
			"param_global": {
				"name": "saida_19",
				"position": [
					[
						0.15625,
						0.5800000000000001
					],
					[
						0.63125,
						0.805
					]
				],
				"exit_type": 3,
				"mask": null,
				"count": 494,
				"capacity": 6,
				"count_in": 201,
				"count_out": 198,
				"count_unknown": 0
			}
		},
		{
			"exit_name": "saida_20",
			"activity": 0,
			"param_global": {
				"name": "saida_20",
				"position": [
					[
						0.15625,
						0.5850000000000001
					],
					[
						0.63125,
						0.805
					]
				],
				"exit_type": 3,
				"mask": null,
				"count": 494,
				"capacity": 6,
				"count_in": 201,
				"count_out": 198,
				"count_unknown": 0
			}
		},
		{
			"exit_name": "saida_21",
			"activity": 0,
			"param_global": {
				"name": "saida_21",
				"position": [
					[
						0.15625,
						0.5900000000000001
					],
					[
						0.63125,
						0.805
					]
				],
				"exit_type": 3,
				"mask": null,
				"count": 494,
				"capacity": 0,
				"count_in": 201,
				"count_out": 201,
				"count_unknown": 0
			}
		},
		{
			"exit_name": "saida_22",
			"activity": 0,
			"param_global": {
				"name": "saida_22",
				"position": [
					[
						0.15625,
						0.5950000000000001
					],
					[
						0.63125,
						0.805
					]
				],
				"exit_type": 3,
				"mask": null,
				"count": 493,
				"capacity": -2,
				"count_in": 200,
				"count_out": 201,
				"count_unknown": 0
			}
		},
		{
			"exit_name": "saida_23",
			"activity": 0,
			"param_global": {
				"name": "saida_23",
				"position": [
					[
						0.15625,
						0.6000000000000001
					],
					[
						0.63125,
						0.805
					]
				],
				"exit_type": 3,
				"mask": null,
				"count": 493,
				"capacity": -2,
				"count_in": 199,
				"count_out": 200,
				"count_unknown": 0
			}
		},
		{
			"exit_name": "saida_24",
			"activity": 0,
			"param_global": {
				"name": "saida_24",
				"position": [
					[
						0.15625,
						0.6050000000000001
					],
					[
						0.63125,
						0.805
					]
				],
				"exit_type": 3,
				"mask": null,
				"count": 493,
				"capacity": -4,
				"count_in": 199,
				"count_out": 201,
				"count_unknown": 0
			}
		},
		{
			"exit_name": "saida_25",
			"activity": 0,
			"param_global": {
				"name": "saida_25",
				"position": [
					[
						0.15625,
						0.6100000000000001
					],
					[
						0.63125,
						0.805
					]
				],
				"exit_type": 3,
				"mask": null,
				"count": 492,
				"capacity": 0,
				"count_in": 200,
				"count_out": 200,
				"count_unknown": 0
			}
		},
		{
			"exit_name": "saida_26",
			"activity": 0,
			"param_global": {
				"name": "saida_26",
				"position": [
					[
						0.15625,
						0.6150000000000001
					],
					[
						0.63125,
						0.805
					]
				],
				"exit_type": 3,
				"mask": null,
				"count": 491,
				"capacity": 2,
				"count_in": 201,
				"count_out": 200,
				"count_unknown": 1
			}
		},
		{
			"exit_name": "saida_27",
			"activity": 0,
			"param_global": {
				"name": "saida_27",
				"position": [
					[
						0.15625,
						0.6200000000000001
					],
					[
						0.63125,
						0.805
					]
				],
				"exit_type": 3,
				"mask": null,
				"count": 490,
				"capacity": 0,
				"count_in": 201,
				"count_out": 201,
				"count_unknown": 0
			}
		},
		{
			"exit_name": "saida_28",
			"activity": 0,
			"param_global": {
				"name": "saida_28",
				"position": [
					[
						0.15625,
						0.6250000000000001
					],
					[
						0.63125,
						0.805
					]
				],
				"exit_type": 3,
				"mask": null,
				"count": 490,
				"capacity": 2,
				"count_in": 201,
				"count_out": 200,
				"count_unknown": 0
			}
		},
		{
			"exit_name": "saida_29",
			"activity": 0,
			"param_global": {
				"name": "saida_29",
				"position": [
					[
						0.15625,
						0.6300000000000001
					],
					[
						0.63125,
						0.805
					]
				],
				"exit_type": 3,
				"mask": null,
				"count": 490,
				"capacity": 4,
				"count_in": 202,
				"count_out": 200,
				"count_unknown": 0
			}
		},
		{
			"exit_name": "saida_30",
			"activity": 0,
			"param_global": {
				"name": "saida_30",
				"position": [
					[
						0.15625,
						0.6350000000000001
					],
					[
						0.63125,
						0.805
					]
				],
				"exit_type": 3,
				"mask": null,
				"count": 489,
				"capacity": 0,
				"count_in": 200,
				"count_out": 200,
				"count_unknown": 0
			}
		},
		{
			"exit_name": "saida_31",
			"activity": 0,
			"param_global": {
				"name": "saida_31",
				"position": [
					[
						0.15625,
						0.6400000000000001
					],
					[
						0.63125,
						0.805
					]
				],
				"exit_type": 3,
				"mask": null,
				"count": 489,
				"capacity": 4,
				"count_in": 200,
				"count_out": 198,
				"count_unknown": 0
			}
		},
		{
			"exit_name": "saida_32",
			"activity": 0,
			"param_global": {
				"name": "saida_32",
				"position": [
					[
						0.15625,
						0.6450000000000001
					],
					[
						0.63125,
						0.805
					]
				],
				"exit_type": 3,
				"mask": null,
				"count": 488,
				"capacity": 6,
				"count_in": 201,
				"count_out": 198,
				"count_unknown": 0
			}
		},
		{
			"exit_name": "saida_33",
			"activity": 0,
			"param_global": {
				"name": "saida_33",
				"position": [
					[
						0.15625,
						0.6500000000000001
					],
					[
						0.63125,
						0.805
					]
				],
				"exit_type": 3,
				"mask": null,
				"count": 487,
				"capacity": 4,
				"count_in": 200,
				"count_out": 198,
				"count_unknown": 0
			}
		},
		{
			"exit_name": "saida_34",
			"activity": 0,
			"param_global": {
				"name": "saida_34",
				"position": [
					[
						0.15625,
						0.6550000000000001
					],
					[
						0.63125,
						0.805
					]
				],
				"exit_type": 3,
				"mask": null,
				"count": 487,
				"capacity": 0,
				"count_in": 198,
				"count_out": 198,
				"count_unknown": 0
			}
		},
		{
			"exit_name": "saida_35",
			"activity": 0,
			"param_global": {
				"name": "saida_35",
				"position": [
					[
						0.15625,
						0.6600000000000001
					],
					[
						0.63125,
						0.805
					]
				],
				"exit_type": 3,
				"mask": null,
				"count": 486,
				"capacity": -2,
				"count_in": 197,
				"count_out": 198,
				"count_unknown": 0
			}
		},
		{
			"exit_name": "saida_36",
			"activity": 0,
			"param_global": {
				"name": "saida_36",
				"position": [
					[
						0.15625,
						0.6650000000000001
					],
					[
						0.63125,
						0.805
					]
				],
				"exit_type": 3,
				"mask": null,
				"count": 486,
				"capacity": -2,
				"count_in": 197,
				"count_out": 198,
				"count_unknown": 0
			}
		},
		{
			"exit_name": "saida_37",
			"activity": 0,
			"param_global": {
				"name": "saida_37",
				"position": [
					[
						0.15625,
						0.6700000000000002
					],
					[
						0.63125,
						0.805
					]
				],
				"exit_type": 3,
				"mask": null,
				"count": 484,
				"capacity": 2,
				"count_in": 197,
				"count_out": 196,
				"count_unknown": 0
			}
		},
		{
			"exit_name": "saida_38",
			"activity": 0,
			"param_global": {
				"name": "saida_38",
				"position": [
					[
						0.15625,
						0.6750000000000002
					],
					[
						0.63125,
						0.805
					]
				],
				"exit_type": 3,
				"mask": null,
				"count": 484,
				"capacity": 0,
				"count_in": 194,
				"count_out": 194,
				"count_unknown": 0
			}
		},
		{
			"exit_name": "saida_39",
			"activity": 0,
			"param_global": {
				"name": "saida_39",
				"position": [
					[
						0.15625,
						0.6800000000000002
					],
					[
						0.63125,
						0.805
					]
				],
				"exit_type": 3,
				"mask": null,
				"count": 484,
				"capacity": 10,
				"count_in": 193,
				"count_out": 188,
				"count_unknown": 0
			}
		}
	],
	"detected_object": [
		{
			"frame_index": 878,
			"centroid": [
				442,
				87
			],
			"gender": [
				"U",
				-1
			],
			"age": [
				-1,
				-1
			],
			"mood": [
				-1,
				-1
			],
			"employee": [
				0,
				0.07074504442925496
			]
		},
		{
			"frame_index": 879,
			"centroid": [
				435,
				93
			],
			"gender": [
				"U",
				-1
			],
			"age": [
				-1,
				-1
			],
			"mood": [
				-1,
				-1
			],
			"employee": [
				0,
				0.046196660482374766
			]
		},
		{
			"frame_index": 880,
			"centroid": [
				382,
				94
			],
			"gender": [
				"U",
				-1
			],
			"age": [
				-1,
				-1
			],
			"mood": [
				-1,
				-1
			],
			"employee": [
				0,
				0.05818137906049994
			]
		},
		{
			"frame_index": 881,
			"centroid": [
				381,
				95
			],
			"gender": [
				"U",
				-1
			],
			"age": [
				-1,
				-1
			],
			"mood": [
				-1,
				-1
			],
			"employee": [
				0,
				0.055954587581093604
			]
		},
		{
			"frame_index": 882,
			"centroid": [
				387,
				96
			],
			"gender": [
				"U",
				-1
			],
			"age": [
				-1,
				-1
			],
			"mood": [
				-1,
				-1
			],
			"employee": [
				0,
				0.05119760479041916
			]
		},
		{
			"frame_index": 883,
			"centroid": [
				386,
				96
			],
			"gender": [
				"U",
				-1
			],
			"age": [
				-1,
				-1
			],
			"mood": [
				-1,
				-1
			],
			"employee": [
				0,
				0.04165526675786594
			]
		},
		{
			"frame_index": 884,
			"centroid": [
				379,
				91
			],
			"gender": [
				"U",
				-1
			],
			"age": [
				-1,
				-1
			],
			"mood": [
				-1,
				-1
			],
			"employee": [
				0,
				0.0442701581540057
			]
		},
		{
			"frame_index": 885,
			"centroid": [
				380,
				91
			],
			"gender": [
				"U",
				-1
			],
			"age": [
				-1,
				-1
			],
			"mood": [
				-1,
				-1
			],
			"employee": [
				0,
				0.04071746530505368
			]
		},
		{
			"frame_index": 886,
			"centroid": [
				383,
				94
			],
			"gender": [
				"U",
				-1
			],
			"age": [
				-1,
				-1
			],
			"mood": [
				-1,
				-1
			],
			"employee": [
				0,
				0.04163070633658869
			]
		},
		{
			"frame_index": 887,
			"centroid": [
				387,
				94
			],
			"gender": [
				"U",
				-1
			],
			"age": [
				-1,
				-1
			],
			"mood": [
				-1,
				-1
			],
			"employee": [
				0,
				0.043583367868490125
			]
		},
		{
			"frame_index": 888,
			"centroid": [
				417,
				94
			],
			"gender": [
				"U",
				-1
			],
			"age": [
				-1,
				-1
			],
			"mood": [
				-1,
				-1
			],
			"employee": [
				0,
				0.03651547805642633
			]
		},
		{
			"frame_index": 889,
			"centroid": [
				422,
				96
			],
			"gender": [
				"U",
				-1
			],
			"age": [
				-1,
				-1
			],
			"mood": [
				-1,
				-1
			],
			"employee": [
				0,
				0.027165932452276064
			]
		},
		{
			"frame_index": 890,
			"centroid": [
				424,
				98
			],
			"gender": [
				"U",
				-1
			],
			"age": [
				-1,
				-1
			],
			"mood": [
				-1,
				-1
			],
			"employee": [
				0,
				0.03415915915915916
			]
		},
		{
			"frame_index": 891,
			"centroid": [
				424,
				98
			],
			"gender": [
				"U",
				-1
			],
			"age": [
				-1,
				-1
			],
			"mood": [
				-1,
				-1
			],
			"employee": [
				0,
				0.02747170935080405
			]
		},
		{
			"frame_index": 892,
			"centroid": [
				421,
				98
			],
			"gender": [
				"U",
				-1
			],
			"age": [
				-1,
				-1
			],
			"mood": [
				-1,
				-1
			],
			"employee": [
				0,
				0.027444422585087547
			]
		},
		{
			"frame_index": 893,
			"centroid": [
				421,
				97
			],
			"gender": [
				"U",
				-1
			],
			"age": [
				-1,
				-1
			],
			"mood": [
				-1,
				-1
			],
			"employee": [
				0,
				0.02475296442687747
			]
		},
		{
			"frame_index": 894,
			"centroid": [
				423,
				96
			],
			"gender": [
				"U",
				-1
			],
			"age": [
				-1,
				-1
			],
			"mood": [
				-1,
				-1
			],
			"employee": [
				0,
				0.01854806541683287
			]
		},
		{
			"frame_index": 895,
			"centroid": [
				424,
				96
			],
			"gender": [
				"U",
				-1
			],
			"age": [
				-1,
				-1
			],
			"mood": [
				-1,
				-1
			],
			"employee": [
				0,
				0.020084304487974214
			]
		},
		{
			"frame_index": 896,
			"centroid": [
				426,
				97
			],
			"gender": [
				"U",
				-1
			],
			"age": [
				-1,
				-1
			],
			"mood": [
				-1,
				-1
			],
			"employee": [
				0,
				0.017649277184160907
			]
		},
		{
			"frame_index": 897,
			"centroid": [
				427,
				98
			],
			"gender": [
				"U",
				-1
			],
			"age": [
				-1,
				-1
			],
			"mood": [
				-1,
				-1
			],
			"employee": [
				0,
				0.01103164942178941
			]
		},
		{
			"frame_index": 898,
			"centroid": [
				426,
				98
			],
			"gender": [
				"U",
				-1
			],
			"age": [
				-1,
				-1
			],
			"mood": [
				-1,
				-1
			],
			"employee": [
				0,
				0.013457688116177105
			]
		},
		{
			"frame_index": 899,
			"centroid": [
				428,
				98
			],
			"gender": [
				"U",
				-1
			],
			"age": [
				-1,
				-1
			],
			"mood": [
				-1,
				-1
			],
			"employee": [
				0,
				0.0121580547112462
			]
		},
		{
			"frame_index": 900,
			"centroid": [
				426,
				99
			],
			"gender": [
				"U",
				-1
			],
			"age": [
				-1,
				-1
			],
			"mood": [
				-1,
				-1
			],
			"employee": [
				0,
				0.023449205873539106
			]
		},
		{
			"frame_index": 901,
			"centroid": [
				427,
				98
			],
			"gender": [
				"U",
				-1
			],
			"age": [
				-1,
				-1
			],
			"mood": [
				-1,
				-1
			],
			"employee": [
				0,
				0.024688879967884384
			]
		},
		{
			"frame_index": 902,
			"centroid": [
				429,
				97
			],
			"gender": [
				"U",
				-1
			],
			"age": [
				-1,
				-1
			],
			"mood": [
				-1,
				-1
			],
			"employee": [
				0,
				0.025113698835524015
			]
		},
		{
			"frame_index": 903,
			"centroid": [
				431,
				98
			],
			"gender": [
				"U",
				-1
			],
			"age": [
				-1,
				-1
			],
			"mood": [
				-1,
				-1
			],
			"employee": [
				0,
				0.022100689241833983
			]
		},
		{
			"frame_index": 904,
			"centroid": [
				425,
				96
			],
			"gender": [
				"U",
				-1
			],
			"age": [
				-1,
				-1
			],
			"mood": [
				-1,
				-1
			],
			"employee": [
				0,
				0.022526598997187234
			]
		},
		{
			"frame_index": 905,
			"centroid": [
				424,
				99
			],
			"gender": [
				"U",
				-1
			],
			"age": [
				-1,
				-1
			],
			"mood": [
				-1,
				-1
			],
			"employee": [
				0,
				0.02683231640079394
			]
		},
		{
			"frame_index": 906,
			"centroid": [
				427,
				99
			],
			"gender": [
				"U",
				-1
			],
			"age": [
				-1,
				-1
			],
			"mood": [
				-1,
				-1
			],
			"employee": [
				0,
				0.018459107450679947
			]
		},
		{
			"frame_index": 907,
			"centroid": [
				429,
				97
			],
			"gender": [
				"U",
				-1
			],
			"age": [
				-1,
				-1
			],
			"mood": [
				-1,
				-1
			],
			"employee": [
				0,
				0.017415193502150025
			]
		},
		{
			"frame_index": 908,
			"centroid": [
				435,
				95
			],
			"gender": [
				"U",
				-1
			],
			"age": [
				-1,
				-1
			],
			"mood": [
				-1,
				-1
			],
			"employee": [
				0,
				0.016502522219553208
			]
		},
		{
			"frame_index": 909,
			"centroid": [
				441,
				96
			],
			"gender": [
				"U",
				-1
			],
			"age": [
				-1,
				-1
			],
			"mood": [
				-1,
				-1
			],
			"employee": [
				0,
				0.019926739926739927
			]
		},
		{
			"frame_index": 910,
			"centroid": [
				443,
				94
			],
			"gender": [
				"U",
				-1
			],
			"age": [
				-1,
				-1
			],
			"mood": [
				-1,
				-1
			],
			"employee": [
				0,
				0.015128293864636377
			]
		},
		{
			"frame_index": 911,
			"centroid": [
				438,
				96
			],
			"gender": [
				"U",
				-1
			],
			"age": [
				-1,
				-1
			],
			"mood": [
				-1,
				-1
			],
			"employee": [
				0,
				0.015289855072463767
			]
		},
		{
			"frame_index": 912,
			"centroid": [
				441,
				96
			],
			"gender": [
				"U",
				-1
			],
			"age": [
				-1,
				-1
			],
			"mood": [
				-1,
				-1
			],
			"employee": [
				0,
				0.01998849582973828
			]
		},
		{
			"frame_index": 913,
			"centroid": [
				443,
				98
			],
			"gender": [
				"U",
				-1
			],
			"age": [
				-1,
				-1
			],
			"mood": [
				-1,
				-1
			],
			"employee": [
				0,
				0.0251270468661773
			]
		},
		{
			"frame_index": 914,
			"centroid": [
				447,
				98
			],
			"gender": [
				"U",
				-1
			],
			"age": [
				-1,
				-1
			],
			"mood": [
				-1,
				-1
			],
			"employee": [
				0,
				0.03137883106786968
			]
		},
		{
			"frame_index": 915,
			"centroid": [
				452,
				99
			],
			"gender": [
				"U",
				-1
			],
			"age": [
				-1,
				-1
			],
			"mood": [
				-1,
				-1
			],
			"employee": [
				0,
				0.03525145067698259
			]
		},
		{
			"frame_index": 916,
			"centroid": [
				454,
				97
			],
			"gender": [
				"U",
				-1
			],
			"age": [
				-1,
				-1
			],
			"mood": [
				-1,
				-1
			],
			"employee": [
				0,
				0.031766012587930395
			]
		},
		{
			"frame_index": 917,
			"centroid": [
				455,
				100
			],
			"gender": [
				"U",
				-1
			],
			"age": [
				-1,
				-1
			],
			"mood": [
				-1,
				-1
			],
			"employee": [
				0,
				0.035694686954352704
			]
		},
		{
			"frame_index": 918,
			"centroid": [
				454,
				98
			],
			"gender": [
				"U",
				-1
			],
			"age": [
				-1,
				-1
			],
			"mood": [
				-1,
				-1
			],
			"employee": [
				0,
				0.035864031147050016
			]
		},
		{
			"frame_index": 919,
			"centroid": [
				453,
				97
			],
			"gender": [
				"U",
				-1
			],
			"age": [
				-1,
				-1
			],
			"mood": [
				-1,
				-1
			],
			"employee": [
				0,
				0.0391502722857283
			]
		},
		{
			"frame_index": 920,
			"centroid": [
				454,
				97
			],
			"gender": [
				"U",
				-1
			],
			"age": [
				-1,
				-1
			],
			"mood": [
				-1,
				-1
			],
			"employee": [
				0,
				0.039595346987472656
			]
		},
		{
			"frame_index": 921,
			"centroid": [
				456,
				98
			],
			"gender": [
				"U",
				-1
			],
			"age": [
				-1,
				-1
			],
			"mood": [
				-1,
				-1
			],
			"employee": [
				0,
				0.035606832342280445
			]
		},
		{
			"frame_index": 922,
			"centroid": [
				462,
				100
			],
			"gender": [
				"U",
				-1
			],
			"age": [
				-1,
				-1
			],
			"mood": [
				-1,
				-1
			],
			"employee": [
				0,
				0.038860103626943004
			]
		},
		{
			"frame_index": 923,
			"centroid": [
				460,
				100
			],
			"gender": [
				"U",
				-1
			],
			"age": [
				-1,
				-1
			],
			"mood": [
				-1,
				-1
			],
			"employee": [
				0,
				0.048982558139534886
			]
		},
		{
			"frame_index": 924,
			"centroid": [
				460,
				100
			],
			"gender": [
				"U",
				-1
			],
			"age": [
				-1,
				-1
			],
			"mood": [
				-1,
				-1
			],
			"employee": [
				0,
				0.053364322533136964
			]
		},
		{
			"frame_index": 925,
			"centroid": [
				461,
				99
			],
			"gender": [
				"U",
				-1
			],
			"age": [
				-1,
				-1
			],
			"mood": [
				-1,
				-1
			],
			"employee": [
				0,
				0.07730569948186529
			]
		},
		{
			"frame_index": 926,
			"centroid": [
				469,
				99
			],
			"gender": [
				"U",
				-1
			],
			"age": [
				-1,
				-1
			],
			"mood": [
				-1,
				-1
			],
			"employee": [
				0,
				0.061513548033938506
			]
		},
		{
			"frame_index": 927,
			"centroid": [
				482,
				100
			],
			"gender": [
				"U",
				-1
			],
			"age": [
				-1,
				-1
			],
			"mood": [
				-1,
				-1
			],
			"employee": [
				0,
				0.030826474791779607
			]
		},
		{
			"frame_index": 928,
			"centroid": [
				484,
				98
			],
			"gender": [
				"U",
				-1
			],
			"age": [
				-1,
				-1
			],
			"mood": [
				-1,
				-1
			],
			"employee": [
				0,
				0.008200290275761975
			]
		},
		{
			"frame_index": 929,
			"centroid": [
				482,
				99
			],
			"gender": [
				"U",
				-1
			],
			"age": [
				-1,
				-1
			],
			"mood": [
				-1,
				-1
			],
			"employee": [
				0,
				0.007649960677772217
			]
		},
		{
			"frame_index": 930,
			"centroid": [
				484,
				99
			],
			"gender": [
				"U",
				-1
			],
			"age": [
				-1,
				-1
			],
			"mood": [
				-1,
				-1
			],
			"employee": [
				0,
				0.009085826111266425
			]
		},
		{
			"frame_index": 931,
			"centroid": [
				489,
				101
			],
			"gender": [
				"U",
				-1
			],
			"age": [
				-1,
				-1
			],
			"mood": [
				-1,
				-1
			],
			"employee": [
				0,
				0.010296846011131726
			]
		},
		{
			"frame_index": 932,
			"centroid": [
				493,
				102
			],
			"gender": [
				"U",
				-1
			],
			"age": [
				-1,
				-1
			],
			"mood": [
				-1,
				-1
			],
			"employee": [
				0,
				0.009690816797415782
			]
		},
		{
			"frame_index": 933,
			"centroid": [
				496,
				105
			],
			"gender": [
				"U",
				-1
			],
			"age": [
				-1,
				-1
			],
			"mood": [
				-1,
				-1
			],
			"employee": [
				0,
				0.0122787762381671
			]
		},
		{
			"frame_index": 934,
			"centroid": [
				496,
				105
			],
			"gender": [
				"U",
				-1
			],
			"age": [
				-1,
				-1
			],
			"mood": [
				-1,
				-1
			],
			"employee": [
				0,
				0.015134529147982063
			]
		},
		{
			"frame_index": 935,
			"centroid": [
				500,
				103
			],
			"gender": [
				"U",
				-1
			],
			"age": [
				-1,
				-1
			],
			"mood": [
				-1,
				-1
			],
			"employee": [
				0,
				0.012292003368919441
			]
		},
		{
			"frame_index": 936,
			"centroid": [
				495,
				103
			],
			"gender": [
				"U",
				-1
			],
			"age": [
				-1,
				-1
			],
			"mood": [
				-1,
				-1
			],
			"employee": [
				0,
				0.015550726606002988
			]
		},
		{
			"frame_index": 937,
			"centroid": [
				492,
				103
			],
			"gender": [
				"U",
				-1
			],
			"age": [
				-1,
				-1
			],
			"mood": [
				-1,
				-1
			],
			"employee": [
				0,
				0.011082811316858263
			]
		},
		{
			"frame_index": 938,
			"centroid": [
				495,
				102
			],
			"gender": [
				"U",
				-1
			],
			"age": [
				-1,
				-1
			],
			"mood": [
				-1,
				-1
			],
			"employee": [
				0,
				0.01179860063108794
			]
		},
		{
			"frame_index": 939,
			"centroid": [
				496,
				102
			],
			"gender": [
				"U",
				-1
			],
			"age": [
				-1,
				-1
			],
			"mood": [
				-1,
				-1
			],
			"employee": [
				0,
				0.013658826759403313
			]
		},
		{
			"frame_index": 940,
			"centroid": [
				501,
				102
			],
			"gender": [
				"U",
				-1
			],
			"age": [
				-1,
				-1
			],
			"mood": [
				-1,
				-1
			],
			"employee": [
				0,
				0.01397819401733296
			]
		},
		{
			"frame_index": 941,
			"centroid": [
				498,
				104
			],
			"gender": [
				"U",
				-1
			],
			"age": [
				-1,
				-1
			],
			"mood": [
				-1,
				-1
			],
			"employee": [
				0,
				0.011482300884955752
			]
		},
		{
			"frame_index": 942,
			"centroid": [
				496,
				103
			],
			"gender": [
				"U",
				-1
			],
			"age": [
				-1,
				-1
			],
			"mood": [
				-1,
				-1
			],
			"employee": [
				0,
				0.010608108108108107
			]
		},
		{
			"frame_index": 943,
			"centroid": [
				495,
				101
			],
			"gender": [
				"U",
				-1
			],
			"age": [
				-1,
				-1
			],
			"mood": [
				-1,
				-1
			],
			"employee": [
				0,
				0.019025367156208277
			]
		},
		{
			"frame_index": 944,
			"centroid": [
				501,
				102
			],
			"gender": [
				"U",
				-1
			],
			"age": [
				-1,
				-1
			],
			"mood": [
				-1,
				-1
			],
			"employee": [
				0,
				0.01545051983057374
			]
		},
		{
			"frame_index": 945,
			"centroid": [
				500,
				102
			],
			"gender": [
				"U",
				-1
			],
			"age": [
				-1,
				-1
			],
			"mood": [
				-1,
				-1
			],
			"employee": [
				0,
				0.016545189504373177
			]
		},
		{
			"frame_index": 946,
			"centroid": [
				498,
				102
			],
			"gender": [
				"U",
				-1
			],
			"age": [
				-1,
				-1
			],
			"mood": [
				-1,
				-1
			],
			"employee": [
				0,
				0.01602232540236245
			]
		},
		{
			"frame_index": 947,
			"centroid": [
				498,
				103
			],
			"gender": [
				"U",
				-1
			],
			"age": [
				-1,
				-1
			],
			"mood": [
				-1,
				-1
			],
			"employee": [
				0,
				0.01515965237769749
			]
		},
		{
			"frame_index": 948,
			"centroid": [
				498,
				103
			],
			"gender": [
				"U",
				-1
			],
			"age": [
				-1,
				-1
			],
			"mood": [
				-1,
				-1
			],
			"employee": [
				0,
				0.015007466401194625
			]
		},
		{
			"frame_index": 949,
			"centroid": [
				502,
				102
			],
			"gender": [
				"U",
				-1
			],
			"age": [
				-1,
				-1
			],
			"mood": [
				-1,
				-1
			],
			"employee": [
				0,
				0.01493212669683258
			]
		},
		{
			"frame_index": 950,
			"centroid": [
				502,
				102
			],
			"gender": [
				"U",
				-1
			],
			"age": [
				-1,
				-1
			],
			"mood": [
				-1,
				-1
			],
			"employee": [
				0,
				0.012830132052821129
			]
		},
		{
			"frame_index": 951,
			"centroid": [
				504,
				102
			],
			"gender": [
				"U",
				-1
			],
			"age": [
				-1,
				-1
			],
			"mood": [
				-1,
				-1
			],
			"employee": [
				0,
				0.011847527472527472
			]
		},
		{
			"frame_index": 952,
			"centroid": [
				506,
				102
			],
			"gender": [
				"U",
				-1
			],
			"age": [
				-1,
				-1
			],
			"mood": [
				-1,
				-1
			],
			"employee": [
				0,
				0.015982076176250932
			]
		},
		{
			"frame_index": 953,
			"centroid": [
				508,
				102
			],
			"gender": [
				"U",
				-1
			],
			"age": [
				-1,
				-1
			],
			"mood": [
				-1,
				-1
			],
			"employee": [
				0,
				0.020889894419306183
			]
		},
		{
			"frame_index": 954,
			"centroid": [
				512,
				104
			],
			"gender": [
				"U",
				-1
			],
			"age": [
				-1,
				-1
			],
			"mood": [
				-1,
				-1
			],
			"employee": [
				0,
				0.01928705440900563
			]
		},
		{
			"frame_index": 955,
			"centroid": [
				513,
				104
			],
			"gender": [
				"U",
				-1
			],
			"age": [
				-1,
				-1
			],
			"mood": [
				-1,
				-1
			],
			"employee": [
				0,
				0.02400369287582705
			]
		},
		{
			"frame_index": 956,
			"centroid": [
				519,
				105
			],
			"gender": [
				"U",
				-1
			],
			"age": [
				-1,
				-1
			],
			"mood": [
				-1,
				-1
			],
			"employee": [
				0,
				0.015853375609001623
			]
		},
		{
			"frame_index": 957,
			"centroid": [
				522,
				104
			],
			"gender": [
				"U",
				-1
			],
			"age": [
				-1,
				-1
			],
			"mood": [
				-1,
				-1
			],
			"employee": [
				0,
				0.016001219140505944
			]
		},
		{
			"frame_index": 958,
			"centroid": [
				512,
				103
			],
			"gender": [
				"U",
				-1
			],
			"age": [
				-1,
				-1
			],
			"mood": [
				-1,
				-1
			],
			"employee": [
				0,
				0.02694183864915572
			]
		},
		{
			"frame_index": 959,
			"centroid": [
				508,
				104
			],
			"gender": [
				"U",
				-1
			],
			"age": [
				-1,
				-1
			],
			"mood": [
				-1,
				-1
			],
			"employee": [
				0,
				0.0350607524520568
			]
		},
		{
			"frame_index": 960,
			"centroid": [
				509,
				105
			],
			"gender": [
				"U",
				-1
			],
			"age": [
				-1,
				-1
			],
			"mood": [
				-1,
				-1
			],
			"employee": [
				0,
				0.07351415094339622
			]
		},
		{
			"frame_index": 961,
			"centroid": [
				503,
				105
			],
			"gender": [
				"U",
				-1
			],
			"age": [
				-1,
				-1
			],
			"mood": [
				-1,
				-1
			],
			"employee": [
				0,
				0.07714778277942726
			]
		},
		{
			"frame_index": 962,
			"centroid": [
				506,
				104
			],
			"gender": [
				"U",
				-1
			],
			"age": [
				-1,
				-1
			],
			"mood": [
				-1,
				-1
			],
			"employee": [
				0,
				0.08332124728063814
			]
		},
		{
			"frame_index": 963,
			"centroid": [
				506,
				103
			],
			"gender": [
				"U",
				-1
			],
			"age": [
				-1,
				-1
			],
			"mood": [
				-1,
				-1
			],
			"employee": [
				0,
				0.08525004250358245
			]
		},
		{
			"frame_index": 964,
			"centroid": [
				508,
				104
			],
			"gender": [
				"U",
				-1
			],
			"age": [
				-1,
				-1
			],
			"mood": [
				-1,
				-1
			],
			"employee": [
				0,
				0.0881516587677725
			]
		},
		{
			"frame_index": 965,
			"centroid": [
				511,
				105
			],
			"gender": [
				"U",
				-1
			],
			"age": [
				-1,
				-1
			],
			"mood": [
				-1,
				-1
			],
			"employee": [
				0,
				0.07174626321545753
			]
		},
		{
			"frame_index": 966,
			"centroid": [
				504,
				104
			],
			"gender": [
				"U",
				-1
			],
			"age": [
				-1,
				-1
			],
			"mood": [
				-1,
				-1
			],
			"employee": [
				0,
				0.06905424688296802
			]
		},
		{
			"frame_index": 967,
			"centroid": [
				504,
				104
			],
			"gender": [
				"U",
				-1
			],
			"age": [
				-1,
				-1
			],
			"mood": [
				-1,
				-1
			],
			"employee": [
				0,
				0.05995574201281637
			]
		},
		{
			"frame_index": 968,
			"centroid": [
				501,
				103
			],
			"gender": [
				"U",
				-1
			],
			"age": [
				-1,
				-1
			],
			"mood": [
				-1,
				-1
			],
			"employee": [
				0,
				0.04848567160124949
			]
		},
		{
			"frame_index": 969,
			"centroid": [
				499,
				102
			],
			"gender": [
				"U",
				-1
			],
			"age": [
				-1,
				-1
			],
			"mood": [
				-1,
				-1
			],
			"employee": [
				0,
				0.04011194029850746
			]
		},
		{
			"frame_index": 970,
			"centroid": [
				502,
				101
			],
			"gender": [
				"U",
				-1
			],
			"age": [
				-1,
				-1
			],
			"mood": [
				-1,
				-1
			],
			"employee": [
				0,
				0.042079889807162534
			]
		},
		{
			"frame_index": 971,
			"centroid": [
				497,
				102
			],
			"gender": [
				"U",
				-1
			],
			"age": [
				-1,
				-1
			],
			"mood": [
				-1,
				-1
			],
			"employee": [
				0,
				0.057708333333333334
			]
		},
		{
			"frame_index": 972,
			"centroid": [
				511,
				102
			],
			"gender": [
				"U",
				-1
			],
			"age": [
				-1,
				-1
			],
			"mood": [
				-1,
				-1
			],
			"employee": [
				0,
				0.05533256880733945
			]
		},
		{
			"frame_index": 973,
			"centroid": [
				508,
				102
			],
			"gender": [
				"U",
				-1
			],
			"age": [
				-1,
				-1
			],
			"mood": [
				-1,
				-1
			],
			"employee": [
				0,
				0.04065249953192286
			]
		},
		{
			"frame_index": 974,
			"centroid": [
				507,
				101
			],
			"gender": [
				"U",
				-1
			],
			"age": [
				-1,
				-1
			],
			"mood": [
				-1,
				-1
			],
			"employee": [
				0,
				0.03418803418803419
			]
		},
		{
			"frame_index": 975,
			"centroid": [
				510,
				100
			],
			"gender": [
				"U",
				-1
			],
			"age": [
				-1,
				-1
			],
			"mood": [
				-1,
				-1
			],
			"employee": [
				0,
				0.03856887298747764
			]
		},
		{
			"frame_index": 976,
			"centroid": [
				512,
				100
			],
			"gender": [
				"U",
				-1
			],
			"age": [
				-1,
				-1
			],
			"mood": [
				-1,
				-1
			],
			"employee": [
				0,
				0.02866826719389917
			]
		},
		{
			"frame_index": 977,
			"centroid": [
				517,
				99
			],
			"gender": [
				"U",
				-1
			],
			"age": [
				-1,
				-1
			],
			"mood": [
				-1,
				-1
			],
			"employee": [
				0,
				0.028240252897787144
			]
		},
		{
			"frame_index": 978,
			"centroid": [
				511,
				99
			],
			"gender": [
				"U",
				-1
			],
			"age": [
				-1,
				-1
			],
			"mood": [
				-1,
				-1
			],
			"employee": [
				0,
				0.021461605164274016
			]
		},
		{
			"frame_index": 979,
			"centroid": [
				509,
				99
			],
			"gender": [
				"U",
				-1
			],
			"age": [
				-1,
				-1
			],
			"mood": [
				-1,
				-1
			],
			"employee": [
				0,
				0.017714534630463193
			]
		},
		{
			"frame_index": 980,
			"centroid": [
				504,
				98
			],
			"gender": [
				"U",
				-1
			],
			"age": [
				-1,
				-1
			],
			"mood": [
				-1,
				-1
			],
			"employee": [
				0,
				0.01984966795592206
			]
		},
		{
			"frame_index": 981,
			"centroid": [
				504,
				98
			],
			"gender": [
				"U",
				-1
			],
			"age": [
				-1,
				-1
			],
			"mood": [
				-1,
				-1
			],
			"employee": [
				0,
				0.02095675355450237
			]
		},
		{
			"frame_index": 982,
			"centroid": [
				502,
				97
			],
			"gender": [
				"U",
				-1
			],
			"age": [
				-1,
				-1
			],
			"mood": [
				-1,
				-1
			],
			"employee": [
				0,
				0.02210863254013548
			]
		},
		{
			"frame_index": 983,
			"centroid": [
				503,
				98
			],
			"gender": [
				"U",
				-1
			],
			"age": [
				-1,
				-1
			],
			"mood": [
				-1,
				-1
			],
			"employee": [
				0,
				0.01723874904652937
			]
		},
		{
			"frame_index": 984,
			"centroid": [
				506,
				97
			],
			"gender": [
				"U",
				-1
			],
			"age": [
				-1,
				-1
			],
			"mood": [
				-1,
				-1
			],
			"employee": [
				0,
				0.017031505728314238
			]
		},
		{
			"frame_index": 985,
			"centroid": [
				507,
				97
			],
			"gender": [
				"U",
				-1
			],
			"age": [
				-1,
				-1
			],
			"mood": [
				-1,
				-1
			],
			"employee": [
				0,
				0.014430826702146713
			]
		},
		{
			"frame_index": 986,
			"centroid": [
				503,
				98
			],
			"gender": [
				"U",
				-1
			],
			"age": [
				-1,
				-1
			],
			"mood": [
				-1,
				-1
			],
			"employee": [
				0,
				0.013961605584642234
			]
		},
		{
			"frame_index": 987,
			"centroid": [
				503,
				99
			],
			"gender": [
				"U",
				-1
			],
			"age": [
				-1,
				-1
			],
			"mood": [
				-1,
				-1
			],
			"employee": [
				0,
				0.014795730585204269
			]
		},
		{
			"frame_index": 988,
			"centroid": [
				504,
				101
			],
			"gender": [
				"U",
				-1
			],
			"age": [
				-1,
				-1
			],
			"mood": [
				-1,
				-1
			],
			"employee": [
				0,
				0.019059065934065936
			]
		},
		{
			"frame_index": 989,
			"centroid": [
				509,
				99
			],
			"gender": [
				"U",
				-1
			],
			"age": [
				-1,
				-1
			],
			"mood": [
				-1,
				-1
			],
			"employee": [
				0,
				0.018837616822429907
			]
		},
		{
			"frame_index": 990,
			"centroid": [
				508,
				98
			],
			"gender": [
				"U",
				-1
			],
			"age": [
				-1,
				-1
			],
			"mood": [
				-1,
				-1
			],
			"employee": [
				0,
				0.01858017135862913
			]
		},
		{
			"frame_index": 991,
			"centroid": [
				505,
				96
			],
			"gender": [
				"U",
				-1
			],
			"age": [
				-1,
				-1
			],
			"mood": [
				-1,
				-1
			],
			"employee": [
				0,
				0.018652622339258285
			]
		},
		{
			"frame_index": 992,
			"centroid": [
				508,
				97
			],
			"gender": [
				"U",
				-1
			],
			"age": [
				-1,
				-1
			],
			"mood": [
				-1,
				-1
			],
			"employee": [
				0,
				0.016679503225185327
			]
		},
		{
			"frame_index": 993,
			"centroid": [
				504,
				97
			],
			"gender": [
				"U",
				-1
			],
			"age": [
				-1,
				-1
			],
			"mood": [
				-1,
				-1
			],
			"employee": [
				0,
				0.016135173726796764
			]
		},
		{
			"frame_index": 994,
			"centroid": [
				506,
				97
			],
			"gender": [
				"U",
				-1
			],
			"age": [
				-1,
				-1
			],
			"mood": [
				-1,
				-1
			],
			"employee": [
				0,
				0.0167517088668528
			]
		},
		{
			"frame_index": 995,
			"centroid": [
				506,
				97
			],
			"gender": [
				"U",
				-1
			],
			"age": [
				-1,
				-1
			],
			"mood": [
				-1,
				-1
			],
			"employee": [
				0,
				0.014609929078014184
			]
		},
		{
			"frame_index": 996,
			"centroid": [
				504,
				95
			],
			"gender": [
				"U",
				-1
			],
			"age": [
				-1,
				-1
			],
			"mood": [
				-1,
				-1
			],
			"employee": [
				0,
				0.013872997711670481
			]
		},
		{
			"frame_index": 997,
			"centroid": [
				504,
				94
			],
			"gender": [
				"U",
				-1
			],
			"age": [
				-1,
				-1
			],
			"mood": [
				-1,
				-1
			],
			"employee": [
				0,
				0.016584250793058405
			]
		},
		{
			"frame_index": 998,
			"centroid": [
				498,
				92
			],
			"gender": [
				"U",
				-1
			],
			"age": [
				-1,
				-1
			],
			"mood": [
				-1,
				-1
			],
			"employee": [
				0,
				0.01741275484292244
			]
		},
		{
			"frame_index": 999,
			"centroid": [
				494,
				92
			],
			"gender": [
				"U",
				-1
			],
			"age": [
				-1,
				-1
			],
			"mood": [
				-1,
				-1
			],
			"employee": [
				0,
				0.024620556681663124
			]
		},
		{
			"frame_index": 1000,
			"centroid": [
				497,
				94
			],
			"gender": [
				"U",
				-1
			],
			"age": [
				-1,
				-1
			],
			"mood": [
				-1,
				-1
			],
			"employee": [
				0,
				0.01978021978021978
			]
		},
		{
			"frame_index": 1001,
			"centroid": [
				497,
				99
			],
			"gender": [
				"U",
				-1
			],
			"age": [
				-1,
				-1
			],
			"mood": [
				-1,
				-1
			],
			"employee": [
				0,
				0.016734279918864097
			]
		},
		{
			"frame_index": 1002,
			"centroid": [
				495,
				98
			],
			"gender": [
				"U",
				-1
			],
			"age": [
				-1,
				-1
			],
			"mood": [
				-1,
				-1
			],
			"employee": [
				0,
				0.013274018798880677
			]
		},
		{
			"frame_index": 1003,
			"centroid": [
				497,
				100
			],
			"gender": [
				"U",
				-1
			],
			"age": [
				-1,
				-1
			],
			"mood": [
				-1,
				-1
			],
			"employee": [
				0,
				0.00992489270386266
			]
		},
		{
			"frame_index": 1004,
			"centroid": [
				500,
				100
			],
			"gender": [
				"U",
				-1
			],
			"age": [
				-1,
				-1
			],
			"mood": [
				-1,
				-1
			],
			"employee": [
				0,
				0.010452027872074325
			]
		},
		{
			"frame_index": 1005,
			"centroid": [
				498,
				101
			],
			"gender": [
				"U",
				-1
			],
			"age": [
				-1,
				-1
			],
			"mood": [
				-1,
				-1
			],
			"employee": [
				0,
				0.014813311688311688
			]
		},
		{
			"frame_index": 1006,
			"centroid": [
				499,
				101
			],
			"gender": [
				"U",
				-1
			],
			"age": [
				-1,
				-1
			],
			"mood": [
				-1,
				-1
			],
			"employee": [
				0,
				0.009380025013400036
			]
		},
		{
			"frame_index": 1007,
			"centroid": [
				498,
				101
			],
			"gender": [
				"U",
				-1
			],
			"age": [
				-1,
				-1
			],
			"mood": [
				-1,
				-1
			],
			"employee": [
				0,
				0.01096830630509387
			]
		},
		{
			"frame_index": 1008,
			"centroid": [
				499,
				102
			],
			"gender": [
				"U",
				-1
			],
			"age": [
				-1,
				-1
			],
			"mood": [
				-1,
				-1
			],
			"employee": [
				0,
				0.007407576762157342
			]
		},
		{
			"frame_index": 1009,
			"centroid": [
				499,
				101
			],
			"gender": [
				"U",
				-1
			],
			"age": [
				-1,
				-1
			],
			"mood": [
				-1,
				-1
			],
			"employee": [
				0,
				0.008977521929824562
			]
		},
		{
			"frame_index": 1010,
			"centroid": [
				502,
				103
			],
			"gender": [
				"U",
				-1
			],
			"age": [
				-1,
				-1
			],
			"mood": [
				-1,
				-1
			],
			"employee": [
				0,
				0.0069987557767508
			]
		},
		{
			"frame_index": 1011,
			"centroid": [
				501,
				100
			],
			"gender": [
				"U",
				-1
			],
			"age": [
				-1,
				-1
			],
			"mood": [
				-1,
				-1
			],
			"employee": [
				0,
				0.009034369885433715
			]
		},
		{
			"frame_index": 1012,
			"centroid": [
				499,
				100
			],
			"gender": [
				"U",
				-1
			],
			"age": [
				-1,
				-1
			],
			"mood": [
				-1,
				-1
			],
			"employee": [
				0,
				0.020188247712878256
			]
		},
		{
			"frame_index": 1013,
			"centroid": [
				496,
				101
			],
			"gender": [
				"U",
				-1
			],
			"age": [
				-1,
				-1
			],
			"mood": [
				-1,
				-1
			],
			"employee": [
				0,
				0.03263068589701756
			]
		},
		{
			"frame_index": 1014,
			"centroid": [
				495,
				94
			],
			"gender": [
				"U",
				-1
			],
			"age": [
				-1,
				-1
			],
			"mood": [
				-1,
				-1
			],
			"employee": [
				0,
				0.0383661394925475
			]
		},
		{
			"frame_index": 1015,
			"centroid": [
				490,
				92
			],
			"gender": [
				"U",
				-1
			],
			"age": [
				-1,
				-1
			],
			"mood": [
				-1,
				-1
			],
			"employee": [
				0,
				0.031096081746673526
			]
		},
		{
			"frame_index": 1016,
			"centroid": [
				492,
				92
			],
			"gender": [
				"U",
				-1
			],
			"age": [
				-1,
				-1
			],
			"mood": [
				-1,
				-1
			],
			"employee": [
				0,
				0.02451762657768751
			]
		},
		{
			"frame_index": 1017,
			"centroid": [
				490,
				94
			],
			"gender": [
				"U",
				-1
			],
			"age": [
				-1,
				-1
			],
			"mood": [
				-1,
				-1
			],
			"employee": [
				0,
				0.011827956989247311
			]
		},
		{
			"frame_index": 1018,
			"centroid": [
				491,
				98
			],
			"gender": [
				"U",
				-1
			],
			"age": [
				-1,
				-1
			],
			"mood": [
				-1,
				-1
			],
			"employee": [
				0,
				0.01544014904517932
			]
		},
		{
			"frame_index": 1019,
			"centroid": [
				485,
				97
			],
			"gender": [
				"U",
				-1
			],
			"age": [
				-1,
				-1
			],
			"mood": [
				-1,
				-1
			],
			"employee": [
				0,
				0.013205741626794259
			]
		},
		{
			"frame_index": 1020,
			"centroid": [
				484,
				100
			],
			"gender": [
				"U",
				-1
			],
			"age": [
				-1,
				-1
			],
			"mood": [
				-1,
				-1
			],
			"employee": [
				0,
				0.011101801424382069
			]
		},
		{
			"frame_index": 1021,
			"centroid": [
				486,
				105
			],
			"gender": [
				"U",
				-1
			],
			"age": [
				-1,
				-1
			],
			"mood": [
				-1,
				-1
			],
			"employee": [
				0,
				0.012510157820452504
			]
		},
		{
			"frame_index": 1022,
			"centroid": [
				485,
				106
			],
			"gender": [
				"U",
				-1
			],
			"age": [
				-1,
				-1
			],
			"mood": [
				-1,
				-1
			],
			"employee": [
				0,
				0.013168296234657791
			]
		},
		{
			"frame_index": 1023,
			"centroid": [
				486,
				105
			],
			"gender": [
				"U",
				-1
			],
			"age": [
				-1,
				-1
			],
			"mood": [
				-1,
				-1
			],
			"employee": [
				0,
				0.011624936126724578
			]
		},
		{
			"frame_index": 1024,
			"centroid": [
				489,
				109
			],
			"gender": [
				"U",
				-1
			],
			"age": [
				-1,
				-1
			],
			"mood": [
				-1,
				-1
			],
			"employee": [
				0,
				0.015039343430070226
			]
		},
		{
			"frame_index": 1025,
			"centroid": [
				490,
				109
			],
			"gender": [
				"U",
				-1
			],
			"age": [
				-1,
				-1
			],
			"mood": [
				-1,
				-1
			],
			"employee": [
				0,
				0.010377962844330558
			]
		},
		{
			"frame_index": 1026,
			"centroid": [
				491,
				107
			],
			"gender": [
				"U",
				-1
			],
			"age": [
				-1,
				-1
			],
			"mood": [
				-1,
				-1
			],
			"employee": [
				0,
				0.01827550669872896
			]
		},
		{
			"frame_index": 1027,
			"centroid": [
				494,
				106
			],
			"gender": [
				"U",
				-1
			],
			"age": [
				-1,
				-1
			],
			"mood": [
				-1,
				-1
			],
			"employee": [
				0,
				0.02287551029984515
			]
		},
		{
			"frame_index": 1028,
			"centroid": [
				492,
				105
			],
			"gender": [
				"U",
				-1
			],
			"age": [
				-1,
				-1
			],
			"mood": [
				-1,
				-1
			],
			"employee": [
				0,
				0.008663366336633664
			]
		},
		{
			"frame_index": 1029,
			"centroid": [
				484,
				101
			],
			"gender": [
				"U",
				-1
			],
			"age": [
				-1,
				-1
			],
			"mood": [
				-1,
				-1
			],
			"employee": [
				0,
				0.010167464114832535
			]
		},
		{
			"frame_index": 1030,
			"centroid": [
				491,
				103
			],
			"gender": [
				"U",
				-1
			],
			"age": [
				-1,
				-1
			],
			"mood": [
				-1,
				-1
			],
			"employee": [
				0,
				0.01180461329715061
			]
		},
		{
			"frame_index": 1031,
			"centroid": [
				493,
				102
			],
			"gender": [
				"U",
				-1
			],
			"age": [
				-1,
				-1
			],
			"mood": [
				-1,
				-1
			],
			"employee": [
				0,
				0.014742014742014743
			]
		},
		{
			"frame_index": 1032,
			"centroid": [
				493,
				102
			],
			"gender": [
				"U",
				-1
			],
			"age": [
				-1,
				-1
			],
			"mood": [
				-1,
				-1
			],
			"employee": [
				0,
				0.00787878787878788
			]
		},
		{
			"frame_index": 1033,
			"centroid": [
				495,
				103
			],
			"gender": [
				"U",
				-1
			],
			"age": [
				-1,
				-1
			],
			"mood": [
				-1,
				-1
			],
			"employee": [
				0,
				0.0071301247771836
			]
		},
		{
			"frame_index": 1034,
			"centroid": [
				494,
				103
			],
			"gender": [
				"U",
				-1
			],
			"age": [
				-1,
				-1
			],
			"mood": [
				-1,
				-1
			],
			"employee": [
				0,
				0.006753223129220764
			]
		},
		{
			"frame_index": 1035,
			"centroid": [
				497,
				107
			],
			"gender": [
				"U",
				-1
			],
			"age": [
				-1,
				-1
			],
			"mood": [
				-1,
				-1
			],
			"employee": [
				0,
				0.0055973923794537484
			]
		},
		{
			"frame_index": 1036,
			"centroid": [
				497,
				109
			],
			"gender": [
				"U",
				-1
			],
			"age": [
				-1,
				-1
			],
			"mood": [
				-1,
				-1
			],
			"employee": [
				0,
				0.005199194124910639
			]
		},
		{
			"frame_index": 1037,
			"centroid": [
				496,
				109
			],
			"gender": [
				"U",
				-1
			],
			"age": [
				-1,
				-1
			],
			"mood": [
				-1,
				-1
			],
			"employee": [
				0,
				0.004185267857142857
			]
		},
		{
			"frame_index": 1038,
			"centroid": [
				494,
				108
			],
			"gender": [
				"U",
				-1
			],
			"age": [
				-1,
				-1
			],
			"mood": [
				-1,
				-1
			],
			"employee": [
				0,
				0.004677581022385567
			]
		},
		{
			"frame_index": 1039,
			"centroid": [
				495,
				109
			],
			"gender": [
				"U",
				-1
			],
			"age": [
				-1,
				-1
			],
			"mood": [
				-1,
				-1
			],
			"employee": [
				0,
				0.0045904649485212145
			]
		},
		{
			"frame_index": 1040,
			"centroid": [
				493,
				107
			],
			"gender": [
				"U",
				-1
			],
			"age": [
				-1,
				-1
			],
			"mood": [
				-1,
				-1
			],
			"employee": [
				0,
				0.006492228998622861
			]
		},
		{
			"frame_index": 1041,
			"centroid": [
				493,
				107
			],
			"gender": [
				"U",
				-1
			],
			"age": [
				-1,
				-1
			],
			"mood": [
				-1,
				-1
			],
			"employee": [
				0,
				0.005857489218357758
			]
		},
		{
			"frame_index": 1042,
			"centroid": [
				498,
				109
			],
			"gender": [
				"U",
				-1
			],
			"age": [
				-1,
				-1
			],
			"mood": [
				-1,
				-1
			],
			"employee": [
				0,
				0.04167946973354989
			]
		},
		{
			"frame_index": 1043,
			"centroid": [
				499,
				107
			],
			"gender": [
				"U",
				-1
			],
			"age": [
				-1,
				-1
			],
			"mood": [
				-1,
				-1
			],
			"employee": [
				0,
				0.03142632347982466
			]
		},
		{
			"frame_index": 1044,
			"centroid": [
				500,
				107
			],
			"gender": [
				"U",
				-1
			],
			"age": [
				-1,
				-1
			],
			"mood": [
				-1,
				-1
			],
			"employee": [
				0,
				0.02225469259300888
			]
		},
		{
			"frame_index": 1045,
			"centroid": [
				499,
				107
			],
			"gender": [
				"U",
				-1
			],
			"age": [
				-1,
				-1
			],
			"mood": [
				-1,
				-1
			],
			"employee": [
				0,
				0.02636843879959537
			]
		},
		{
			"frame_index": 1046,
			"centroid": [
				499,
				107
			],
			"gender": [
				"U",
				-1
			],
			"age": [
				-1,
				-1
			],
			"mood": [
				-1,
				-1
			],
			"employee": [
				0,
				0.01869281045751634
			]
		},
		{
			"frame_index": 1047,
			"centroid": [
				500,
				108
			],
			"gender": [
				"U",
				-1
			],
			"age": [
				-1,
				-1
			],
			"mood": [
				-1,
				-1
			],
			"employee": [
				0,
				0.00821687370600414
			]
		},
		{
			"frame_index": 1048,
			"centroid": [
				500,
				108
			],
			"gender": [
				"U",
				-1
			],
			"age": [
				-1,
				-1
			],
			"mood": [
				-1,
				-1
			],
			"employee": [
				0,
				0.010613052076466711
			]
		},
		{
			"frame_index": 1049,
			"centroid": [
				501,
				108
			],
			"gender": [
				"U",
				-1
			],
			"age": [
				-1,
				-1
			],
			"mood": [
				-1,
				-1
			],
			"employee": [
				0,
				0.0058355777863280745
			]
		},
		{
			"frame_index": 1050,
			"centroid": [
				498,
				107
			],
			"gender": [
				"U",
				-1
			],
			"age": [
				-1,
				-1
			],
			"mood": [
				-1,
				-1
			],
			"employee": [
				0,
				0.01887868229331644
			]
		},
		{
			"frame_index": 1051,
			"centroid": [
				438,
				110
			],
			"gender": [
				"U",
				-1
			],
			"age": [
				-1,
				-1
			],
			"mood": [
				-1,
				-1
			],
			"employee": [
				0,
				0.04849586776859504
			]
		},
		{
			"frame_index": 1052,
			"centroid": [
				435,
				111
			],
			"gender": [
				"U",
				-1
			],
			"age": [
				-1,
				-1
			],
			"mood": [
				-1,
				-1
			],
			"employee": [
				0,
				0.05749128919860627
			]
		},
		{
			"frame_index": 1053,
			"centroid": [
				440,
				111
			],
			"gender": [
				"U",
				-1
			],
			"age": [
				-1,
				-1
			],
			"mood": [
				-1,
				-1
			],
			"employee": [
				0,
				0.06525974025974025
			]
		},
		{
			"frame_index": 1054,
			"centroid": [
				443,
				111
			],
			"gender": [
				"U",
				-1
			],
			"age": [
				-1,
				-1
			],
			"mood": [
				-1,
				-1
			],
			"employee": [
				0,
				0.05957966764418377
			]
		},
		{
			"frame_index": 1055,
			"centroid": [
				445,
				110
			],
			"gender": [
				"U",
				-1
			],
			"age": [
				-1,
				-1
			],
			"mood": [
				-1,
				-1
			],
			"employee": [
				0,
				0.052207001522070015
			]
		},
		{
			"frame_index": 1056,
			"centroid": [
				439,
				110
			],
			"gender": [
				"U",
				-1
			],
			"age": [
				-1,
				-1
			],
			"mood": [
				-1,
				-1
			],
			"employee": [
				0,
				0.061668742216687424
			]
		},
		{
			"frame_index": 1057,
			"centroid": [
				434,
				111
			],
			"gender": [
				"U",
				-1
			],
			"age": [
				-1,
				-1
			],
			"mood": [
				-1,
				-1
			],
			"employee": [
				0,
				0.03613856141890767
			]
		},
		{
			"frame_index": 1058,
			"centroid": [
				439,
				112
			],
			"gender": [
				"U",
				-1
			],
			"age": [
				-1,
				-1
			],
			"mood": [
				-1,
				-1
			],
			"employee": [
				0,
				0.02974180734856008
			]
		},
		{
			"frame_index": 1059,
			"centroid": [
				504,
				108
			],
			"gender": [
				"U",
				-1
			],
			"age": [
				-1,
				-1
			],
			"mood": [
				-1,
				-1
			],
			"employee": [
				0,
				0.03609756097560975
			]
		},
		{
			"frame_index": 1060,
			"centroid": [
				501,
				109
			],
			"gender": [
				"U",
				-1
			],
			"age": [
				-1,
				-1
			],
			"mood": [
				-1,
				-1
			],
			"employee": [
				0,
				0.031618997638415115
			]
		},
		{
			"frame_index": 1061,
			"centroid": [
				502,
				108
			],
			"gender": [
				"U",
				-1
			],
			"age": [
				-1,
				-1
			],
			"mood": [
				-1,
				-1
			],
			"employee": [
				0,
				0.028186638388123013
			]
		},
		{
			"frame_index": 1062,
			"centroid": [
				501,
				108
			],
			"gender": [
				"U",
				-1
			],
			"age": [
				-1,
				-1
			],
			"mood": [
				-1,
				-1
			],
			"employee": [
				0,
				0.028275401069518716
			]
		},
		{
			"frame_index": 1063,
			"centroid": [
				498,
				106
			],
			"gender": [
				"U",
				-1
			],
			"age": [
				-1,
				-1
			],
			"mood": [
				-1,
				-1
			],
			"employee": [
				0,
				0.02074388755818683
			]
		},
		{
			"frame_index": 1064,
			"centroid": [
				497,
				106
			],
			"gender": [
				"U",
				-1
			],
			"age": [
				-1,
				-1
			],
			"mood": [
				-1,
				-1
			],
			"employee": [
				0,
				0.02614408906328421
			]
		},
		{
			"frame_index": 1065,
			"centroid": [
				498,
				105
			],
			"gender": [
				"U",
				-1
			],
			"age": [
				-1,
				-1
			],
			"mood": [
				-1,
				-1
			],
			"employee": [
				0,
				0.013059701492537313
			]
		},
		{
			"frame_index": 1066,
			"centroid": [
				497,
				105
			],
			"gender": [
				"U",
				-1
			],
			"age": [
				-1,
				-1
			],
			"mood": [
				-1,
				-1
			],
			"employee": [
				0,
				0.016282225237449117
			]
		},
		{
			"frame_index": 1067,
			"centroid": [
				497,
				105
			],
			"gender": [
				"U",
				-1
			],
			"age": [
				-1,
				-1
			],
			"mood": [
				-1,
				-1
			],
			"employee": [
				0,
				0.0163372327551432
			]
		},
		{
			"frame_index": 1068,
			"centroid": [
				496,
				106
			],
			"gender": [
				"U",
				-1
			],
			"age": [
				-1,
				-1
			],
			"mood": [
				-1,
				-1
			],
			"employee": [
				0,
				0.018461538461538463
			]
		},
		{
			"frame_index": 1069,
			"centroid": [
				495,
				104
			],
			"gender": [
				"U",
				-1
			],
			"age": [
				-1,
				-1
			],
			"mood": [
				-1,
				-1
			],
			"employee": [
				0,
				0.015760621288259478
			]
		},
		{
			"frame_index": 1070,
			"centroid": [
				494,
				104
			],
			"gender": [
				"U",
				-1
			],
			"age": [
				-1,
				-1
			],
			"mood": [
				-1,
				-1
			],
			"employee": [
				0,
				0.017415846355062985
			]
		},
		{
			"frame_index": 1071,
			"centroid": [
				494,
				104
			],
			"gender": [
				"U",
				-1
			],
			"age": [
				-1,
				-1
			],
			"mood": [
				-1,
				-1
			],
			"employee": [
				0,
				0.017715304633767918
			]
		},
		{
			"frame_index": 1072,
			"centroid": [
				495,
				104
			],
			"gender": [
				"U",
				-1
			],
			"age": [
				-1,
				-1
			],
			"mood": [
				-1,
				-1
			],
			"employee": [
				0,
				0.01792371998240048
			]
		},
		{
			"frame_index": 1073,
			"centroid": [
				496,
				101
			],
			"gender": [
				"U",
				-1
			],
			"age": [
				-1,
				-1
			],
			"mood": [
				-1,
				-1
			],
			"employee": [
				0,
				0.01997514828968654
			]
		},
		{
			"frame_index": 1074,
			"centroid": [
				496,
				103
			],
			"gender": [
				"U",
				-1
			],
			"age": [
				-1,
				-1
			],
			"mood": [
				-1,
				-1
			],
			"employee": [
				0,
				0.021374428080398807
			]
		},
		{
			"frame_index": 1075,
			"centroid": [
				496,
				103
			],
			"gender": [
				"U",
				-1
			],
			"age": [
				-1,
				-1
			],
			"mood": [
				-1,
				-1
			],
			"employee": [
				0,
				0.01953710006807352
			]
		},
		{
			"frame_index": 1076,
			"centroid": [
				495,
				101
			],
			"gender": [
				"U",
				-1
			],
			"age": [
				-1,
				-1
			],
			"mood": [
				-1,
				-1
			],
			"employee": [
				0,
				0.021443346357159273
			]
		},
		{
			"frame_index": 1077,
			"centroid": [
				496,
				99
			],
			"gender": [
				"U",
				-1
			],
			"age": [
				-1,
				-1
			],
			"mood": [
				-1,
				-1
			],
			"employee": [
				0,
				0.02316522220173336
			]
		},
		{
			"frame_index": 1078,
			"centroid": [
				496,
				99
			],
			"gender": [
				"U",
				-1
			],
			"age": [
				-1,
				-1
			],
			"mood": [
				-1,
				-1
			],
			"employee": [
				0,
				0.02059025394646534
			]
		},
		{
			"frame_index": 1079,
			"centroid": [
				495,
				99
			],
			"gender": [
				"U",
				-1
			],
			"age": [
				-1,
				-1
			],
			"mood": [
				-1,
				-1
			],
			"employee": [
				0,
				0.020597299012054746
			]
		},
		{
			"frame_index": 1080,
			"centroid": [
				493,
				99
			],
			"gender": [
				"U",
				-1
			],
			"age": [
				-1,
				-1
			],
			"mood": [
				-1,
				-1
			],
			"employee": [
				0,
				0.030389363722697058
			]
		},
		{
			"frame_index": 1081,
			"centroid": [
				496,
				99
			],
			"gender": [
				"U",
				-1
			],
			"age": [
				-1,
				-1
			],
			"mood": [
				-1,
				-1
			],
			"employee": [
				0,
				0.02992854895969083
			]
		},
		{
			"frame_index": 1082,
			"centroid": [
				496,
				98
			],
			"gender": [
				"U",
				-1
			],
			"age": [
				-1,
				-1
			],
			"mood": [
				-1,
				-1
			],
			"employee": [
				0,
				0.0309894640403115
			]
		},
		{
			"frame_index": 1083,
			"centroid": [
				495,
				97
			],
			"gender": [
				"U",
				-1
			],
			"age": [
				-1,
				-1
			],
			"mood": [
				-1,
				-1
			],
			"employee": [
				0,
				0.03143918547055586
			]
		},
		{
			"frame_index": 1084,
			"centroid": [
				495,
				95
			],
			"gender": [
				"U",
				-1
			],
			"age": [
				-1,
				-1
			],
			"mood": [
				-1,
				-1
			],
			"employee": [
				0,
				0.03349304234199124
			]
		},
		{
			"frame_index": 1085,
			"centroid": [
				495,
				94
			],
			"gender": [
				"U",
				-1
			],
			"age": [
				-1,
				-1
			],
			"mood": [
				-1,
				-1
			],
			"employee": [
				0,
				0.031243534036830126
			]
		},
		{
			"frame_index": 1086,
			"centroid": [
				496,
				93
			],
			"gender": [
				"U",
				-1
			],
			"age": [
				-1,
				-1
			],
			"mood": [
				-1,
				-1
			],
			"employee": [
				0,
				0.030923555863023176
			]
		},
		{
			"frame_index": 1087,
			"centroid": [
				497,
				95
			],
			"gender": [
				"U",
				-1
			],
			"age": [
				-1,
				-1
			],
			"mood": [
				-1,
				-1
			],
			"employee": [
				0,
				0.03178500784393971
			]
		},
		{
			"frame_index": 1088,
			"centroid": [
				498,
				95
			],
			"gender": [
				"U",
				-1
			],
			"age": [
				-1,
				-1
			],
			"mood": [
				-1,
				-1
			],
			"employee": [
				0,
				0.03230027548209367
			]
		},
		{
			"frame_index": 1089,
			"centroid": [
				498,
				99
			],
			"gender": [
				"U",
				-1
			],
			"age": [
				-1,
				-1
			],
			"mood": [
				-1,
				-1
			],
			"employee": [
				0,
				0.035864232995978254
			]
		},
		{
			"frame_index": 1090,
			"centroid": [
				498,
				103
			],
			"gender": [
				"U",
				-1
			],
			"age": [
				-1,
				-1
			],
			"mood": [
				-1,
				-1
			],
			"employee": [
				0,
				0.03518198682274675
			]
		},
		{
			"frame_index": 1091,
			"centroid": [
				500,
				100
			],
			"gender": [
				"U",
				-1
			],
			"age": [
				-1,
				-1
			],
			"mood": [
				-1,
				-1
			],
			"employee": [
				0,
				0.030737704918032786
			]
		},
		{
			"frame_index": 1092,
			"centroid": [
				499,
				97
			],
			"gender": [
				"U",
				-1
			],
			"age": [
				-1,
				-1
			],
			"mood": [
				-1,
				-1
			],
			"employee": [
				0,
				0.020701319201713836
			]
		},
		{
			"frame_index": 1093,
			"centroid": [
				500,
				99
			],
			"gender": [
				"U",
				-1
			],
			"age": [
				-1,
				-1
			],
			"mood": [
				-1,
				-1
			],
			"employee": [
				0,
				0.02029024455791454
			]
		},
		{
			"frame_index": 1094,
			"centroid": [
				499,
				104
			],
			"gender": [
				"U",
				-1
			],
			"age": [
				-1,
				-1
			],
			"mood": [
				-1,
				-1
			],
			"employee": [
				0,
				0.022794348508634224
			]
		}
	]
}