{
	"json_type": "people_count",
	"branch_name": "teste",
	"host_name": "host_name",
	"mac_address_device": "dc:a6:32:6b:8e:7e",
	"mac_address_count": "0c:9d:92:8e:bf:f0",
	"video_name": "debugRasp_dca6326b8e7e_2021-02-11_14-26-55-134774",
	"width": 800,
	"height": 600,
	"person_id": 926,
	"timestamp_registered": 1613064452.1431477,
	"exits": [
		{
			"exit_name": "saida_0",
			"activity": 0,
			"param_global": {
				"name": "saida_0",
				"position": [
					[
						0.15625,
						0.485
					],
					[
						0.63125,
						0.805
					]
				],
				"exit_type": 1,
				"mask": null,
				"count": 0,
				"capacity": 0,
				"count_in": 0,
				"count_out": 0,
				"count_unknown": 0
			}
		},
		{
			"exit_name": "saida_1",
			"activity": 1,
			"param_global": {
				"name": "saida_1",
				"position": [
					[
						0.15625,
						0.49
					],
					[
						0.63125,
						0.805
					]
				],
				"exit_type": 3,
				"mask": null,
				"count": 523,
				"capacity": 6,
				"count_in": 198,
				"count_out": 195,
				"count_unknown": 0
			}
		},
		{
			"exit_name": "saida_2",
			"activity": 1,
			"param_global": {
				"name": "saida_2",
				"position": [
					[
						0.15625,
						0.495
					],
					[
						0.63125,
						0.805
					]
				],
				"exit_type": 3,
				"mask": null,
				"count": 520,
				"capacity": 4,
				"count_in": 198,
				"count_out": 196,
				"count_unknown": 0
			}
		},
		{
			"exit_name": "saida_3",
			"activity": 1,
			"param_global": {
				"name": "saida_3",
				"position": [
					[
						0.15625,
						0.5
					],
					[
						0.63125,
						0.805
					]
				],
				"exit_type": 3,
				"mask": null,
				"count": 519,
				"capacity": 6,
				"count_in": 199,
				"count_out": 196,
				"count_unknown": 0
			}
		},
		{
			"exit_name": "saida_4",
			"activity": 1,
			"param_global": {
				"name": "saida_4",
				"position": [
					[
						0.15625,
						0.505
					],
					[
						0.63125,
						0.805
					]
				],
				"exit_type": 3,
				"mask": null,
				"count": 517,
				"capacity": 4,
				"count_in": 198,
				"count_out": 196,
				"count_unknown": 0
			}
		},
		{
			"exit_name": "saida_5",
			"activity": 1,
			"param_global": {
				"name": "saida_5",
				"position": [
					[
						0.15625,
						0.51
					],
					[
						0.63125,
						0.805
					]
				],
				"exit_type": 3,
				"mask": null,
				"count": 513,
				"capacity": 6,
				"count_in": 198,
				"count_out": 195,
				"count_unknown": 0
			}
		},
		{
			"exit_name": "saida_6",
			"activity": 1,
			"param_global": {
				"name": "saida_6",
				"position": [
					[
						0.15625,
						0.515
					],
					[
						0.63125,
						0.805
					]
				],
				"exit_type": 3,
				"mask": null,
				"count": 511,
				"capacity": 2,
				"count_in": 197,
				"count_out": 196,
				"count_unknown": 0
			}
		},
		{
			"exit_name": "saida_7",
			"activity": 1,
			"param_global": {
				"name": "saida_7",
				"position": [
					[
						0.15625,
						0.52
					],
					[
						0.63125,
						0.805
					]
				],
				"exit_type": 3,
				"mask": null,
				"count": 510,
				"capacity": 6,
				"count_in": 198,
				"count_out": 195,
				"count_unknown": 0
			}
		},
		{
			"exit_name": "saida_8",
			"activity": 1,
			"param_global": {
				"name": "saida_8",
				"position": [
					[
						0.15625,
						0.525
					],
					[
						0.63125,
						0.805
					]
				],
				"exit_type": 3,
				"mask": null,
				"count": 510,
				"capacity": 2,
				"count_in": 197,
				"count_out": 196,
				"count_unknown": 0
			}
		},
		{
			"exit_name": "saida_9",
			"activity": 1,
			"param_global": {
				"name": "saida_9",
				"position": [
					[
						0.15625,
						0.53
					],
					[
						0.63125,
						0.805
					]
				],
				"exit_type": 3,
				"mask": null,
				"count": 507,
				"capacity": 2,
				"count_in": 198,
				"count_out": 197,
				"count_unknown": 0
			}
		},
		{
			"exit_name": "saida_10",
			"activity": 1,
			"param_global": {
				"name": "saida_10",
				"position": [
					[
						0.15625,
						0.535
					],
					[
						0.63125,
						0.805
					]
				],
				"exit_type": 3,
				"mask": null,
				"count": 506,
				"capacity": 6,
				"count_in": 199,
				"count_out": 196,
				"count_unknown": 0
			}
		},
		{
			"exit_name": "saida_11",
			"activity": 1,
			"param_global": {
				"name": "saida_11",
				"position": [
					[
						0.15625,
						0.54
					],
					[
						0.63125,
						0.805
					]
				],
				"exit_type": 3,
				"mask": null,
				"count": 501,
				"capacity": 8,
				"count_in": 200,
				"count_out": 196,
				"count_unknown": 0
			}
		},
		{
			"exit_name": "saida_12",
			"activity": 1,
			"param_global": {
				"name": "saida_12",
				"position": [
					[
						0.15625,
						0.545
					],
					[
						0.63125,
						0.805
					]
				],
				"exit_type": 3,
				"mask": null,
				"count": 498,
				"capacity": 10,
				"count_in": 201,
				"count_out": 196,
				"count_unknown": 0
			}
		},
		{
			"exit_name": "saida_13",
			"activity": 1,
			"param_global": {
				"name": "saida_13",
				"position": [
					[
						0.15625,
						0.55
					],
					[
						0.63125,
						0.805
					]
				],
				"exit_type": 3,
				"mask": null,
				"count": 497,
				"capacity": 12,
				"count_in": 201,
				"count_out": 195,
				"count_unknown": 0
			}
		},
		{
			"exit_name": "saida_14",
			"activity": 1,
			"param_global": {
				"name": "saida_14",
				"position": [
					[
						0.15625,
						0.555
					],
					[
						0.63125,
						0.805
					]
				],
				"exit_type": 3,
				"mask": null,
				"count": 495,
				"capacity": 8,
				"count_in": 201,
				"count_out": 197,
				"count_unknown": 0
			}
		},
		{
			"exit_name": "saida_15",
			"activity": 1,
			"param_global": {
				"name": "saida_15",
				"position": [
					[
						0.15625,
						0.56
					],
					[
						0.63125,
						0.805
					]
				],
				"exit_type": 3,
				"mask": null,
				"count": 493,
				"capacity": 4,
				"count_in": 199,
				"count_out": 197,
				"count_unknown": 0
			}
		},
		{
			"exit_name": "saida_16",
			"activity": 1,
			"param_global": {
				"name": "saida_16",
				"position": [
					[
						0.15625,
						0.5650000000000001
					],
					[
						0.63125,
						0.805
					]
				],
				"exit_type": 3,
				"mask": null,
				"count": 491,
				"capacity": 12,
				"count_in": 201,
				"count_out": 195,
				"count_unknown": 0
			}
		},
		{
			"exit_name": "saida_17",
			"activity": 1,
			"param_global": {
				"name": "saida_17",
				"position": [
					[
						0.15625,
						0.5700000000000001
					],
					[
						0.63125,
						0.805
					]
				],
				"exit_type": 3,
				"mask": null,
				"count": 491,
				"capacity": 10,
				"count_in": 200,
				"count_out": 195,
				"count_unknown": 0
			}
		},
		{
			"exit_name": "saida_18",
			"activity": 1,
			"param_global": {
				"name": "saida_18",
				"position": [
					[
						0.15625,
						0.5750000000000001
					],
					[
						0.63125,
						0.805
					]
				],
				"exit_type": 3,
				"mask": null,
				"count": 490,
				"capacity": 10,
				"count_in": 200,
				"count_out": 195,
				"count_unknown": 0
			}
		},
		{
			"exit_name": "saida_19",
			"activity": 1,
			"param_global": {
				"name": "saida_19",
				"position": [
					[
						0.15625,
						0.5800000000000001
					],
					[
						0.63125,
						0.805
					]
				],
				"exit_type": 3,
				"mask": null,
				"count": 489,
				"capacity": 12,
				"count_in": 200,
				"count_out": 194,
				"count_unknown": 0
			}
		},
		{
			"exit_name": "saida_20",
			"activity": 1,
			"param_global": {
				"name": "saida_20",
				"position": [
					[
						0.15625,
						0.5850000000000001
					],
					[
						0.63125,
						0.805
					]
				],
				"exit_type": 3,
				"mask": null,
				"count": 489,
				"capacity": 12,
				"count_in": 200,
				"count_out": 194,
				"count_unknown": 0
			}
		},
		{
			"exit_name": "saida_21",
			"activity": 1,
			"param_global": {
				"name": "saida_21",
				"position": [
					[
						0.15625,
						0.5900000000000001
					],
					[
						0.63125,
						0.805
					]
				],
				"exit_type": 3,
				"mask": null,
				"count": 489,
				"capacity": 6,
				"count_in": 200,
				"count_out": 197,
				"count_unknown": 0
			}
		},
		{
			"exit_name": "saida_22",
			"activity": 1,
			"param_global": {
				"name": "saida_22",
				"position": [
					[
						0.15625,
						0.5950000000000001
					],
					[
						0.63125,
						0.805
					]
				],
				"exit_type": 3,
				"mask": null,
				"count": 488,
				"capacity": 4,
				"count_in": 199,
				"count_out": 197,
				"count_unknown": 0
			}
		},
		{
			"exit_name": "saida_23",
			"activity": 1,
			"param_global": {
				"name": "saida_23",
				"position": [
					[
						0.15625,
						0.6000000000000001
					],
					[
						0.63125,
						0.805
					]
				],
				"exit_type": 3,
				"mask": null,
				"count": 488,
				"capacity": 4,
				"count_in": 198,
				"count_out": 196,
				"count_unknown": 0
			}
		},
		{
			"exit_name": "saida_24",
			"activity": 1,
			"param_global": {
				"name": "saida_24",
				"position": [
					[
						0.15625,
						0.6050000000000001
					],
					[
						0.63125,
						0.805
					]
				],
				"exit_type": 3,
				"mask": null,
				"count": 488,
				"capacity": 2,
				"count_in": 198,
				"count_out": 197,
				"count_unknown": 0
			}
		},
		{
			"exit_name": "saida_25",
			"activity": 1,
			"param_global": {
				"name": "saida_25",
				"position": [
					[
						0.15625,
						0.6100000000000001
					],
					[
						0.63125,
						0.805
					]
				],
				"exit_type": 3,
				"mask": null,
				"count": 487,
				"capacity": 6,
				"count_in": 199,
				"count_out": 196,
				"count_unknown": 0
			}
		},
		{
			"exit_name": "saida_26",
			"activity": 1,
			"param_global": {
				"name": "saida_26",
				"position": [
					[
						0.15625,
						0.6150000000000001
					],
					[
						0.63125,
						0.805
					]
				],
				"exit_type": 3,
				"mask": null,
				"count": 486,
				"capacity": 8,
				"count_in": 200,
				"count_out": 196,
				"count_unknown": 1
			}
		},
		{
			"exit_name": "saida_27",
			"activity": 1,
			"param_global": {
				"name": "saida_27",
				"position": [
					[
						0.15625,
						0.6200000000000001
					],
					[
						0.63125,
						0.805
					]
				],
				"exit_type": 3,
				"mask": null,
				"count": 485,
				"capacity": 6,
				"count_in": 200,
				"count_out": 197,
				"count_unknown": 0
			}
		},
		{
			"exit_name": "saida_28",
			"activity": 1,
			"param_global": {
				"name": "saida_28",
				"position": [
					[
						0.15625,
						0.6250000000000001
					],
					[
						0.63125,
						0.805
					]
				],
				"exit_type": 3,
				"mask": null,
				"count": 485,
				"capacity": 8,
				"count_in": 200,
				"count_out": 196,
				"count_unknown": 0
			}
		},
		{
			"exit_name": "saida_29",
			"activity": 1,
			"param_global": {
				"name": "saida_29",
				"position": [
					[
						0.15625,
						0.6300000000000001
					],
					[
						0.63125,
						0.805
					]
				],
				"exit_type": 3,
				"mask": null,
				"count": 485,
				"capacity": 10,
				"count_in": 201,
				"count_out": 196,
				"count_unknown": 0
			}
		},
		{
			"exit_name": "saida_30",
			"activity": 1,
			"param_global": {
				"name": "saida_30",
				"position": [
					[
						0.15625,
						0.6350000000000001
					],
					[
						0.63125,
						0.805
					]
				],
				"exit_type": 3,
				"mask": null,
				"count": 484,
				"capacity": 6,
				"count_in": 199,
				"count_out": 196,
				"count_unknown": 0
			}
		},
		{
			"exit_name": "saida_31",
			"activity": 1,
			"param_global": {
				"name": "saida_31",
				"position": [
					[
						0.15625,
						0.6400000000000001
					],
					[
						0.63125,
						0.805
					]
				],
				"exit_type": 3,
				"mask": null,
				"count": 484,
				"capacity": 10,
				"count_in": 199,
				"count_out": 194,
				"count_unknown": 0
			}
		},
		{
			"exit_name": "saida_32",
			"activity": 1,
			"param_global": {
				"name": "saida_32",
				"position": [
					[
						0.15625,
						0.6450000000000001
					],
					[
						0.63125,
						0.805
					]
				],
				"exit_type": 3,
				"mask": null,
				"count": 483,
				"capacity": 12,
				"count_in": 200,
				"count_out": 194,
				"count_unknown": 0
			}
		},
		{
			"exit_name": "saida_33",
			"activity": 1,
			"param_global": {
				"name": "saida_33",
				"position": [
					[
						0.15625,
						0.6500000000000001
					],
					[
						0.63125,
						0.805
					]
				],
				"exit_type": 3,
				"mask": null,
				"count": 482,
				"capacity": 10,
				"count_in": 199,
				"count_out": 194,
				"count_unknown": 0
			}
		},
		{
			"exit_name": "saida_34",
			"activity": 1,
			"param_global": {
				"name": "saida_34",
				"position": [
					[
						0.15625,
						0.6550000000000001
					],
					[
						0.63125,
						0.805
					]
				],
				"exit_type": 3,
				"mask": null,
				"count": 482,
				"capacity": 6,
				"count_in": 197,
				"count_out": 194,
				"count_unknown": 0
			}
		},
		{
			"exit_name": "saida_35",
			"activity": 1,
			"param_global": {
				"name": "saida_35",
				"position": [
					[
						0.15625,
						0.6600000000000001
					],
					[
						0.63125,
						0.805
					]
				],
				"exit_type": 3,
				"mask": null,
				"count": 481,
				"capacity": 4,
				"count_in": 196,
				"count_out": 194,
				"count_unknown": 0
			}
		},
		{
			"exit_name": "saida_36",
			"activity": 1,
			"param_global": {
				"name": "saida_36",
				"position": [
					[
						0.15625,
						0.6650000000000001
					],
					[
						0.63125,
						0.805
					]
				],
				"exit_type": 3,
				"mask": null,
				"count": 481,
				"capacity": 4,
				"count_in": 196,
				"count_out": 194,
				"count_unknown": 0
			}
		},
		{
			"exit_name": "saida_37",
			"activity": 1,
			"param_global": {
				"name": "saida_37",
				"position": [
					[
						0.15625,
						0.6700000000000002
					],
					[
						0.63125,
						0.805
					]
				],
				"exit_type": 3,
				"mask": null,
				"count": 479,
				"capacity": 8,
				"count_in": 196,
				"count_out": 192,
				"count_unknown": 0
			}
		},
		{
			"exit_name": "saida_38",
			"activity": 1,
			"param_global": {
				"name": "saida_38",
				"position": [
					[
						0.15625,
						0.6750000000000002
					],
					[
						0.63125,
						0.805
					]
				],
				"exit_type": 3,
				"mask": null,
				"count": 479,
				"capacity": 6,
				"count_in": 193,
				"count_out": 190,
				"count_unknown": 0
			}
		},
		{
			"exit_name": "saida_39",
			"activity": 1,
			"param_global": {
				"name": "saida_39",
				"position": [
					[
						0.15625,
						0.6800000000000002
					],
					[
						0.63125,
						0.805
					]
				],
				"exit_type": 3,
				"mask": null,
				"count": 479,
				"capacity": 16,
				"count_in": 192,
				"count_out": 184,
				"count_unknown": 0
			}
		}
	],
	"detected_object": [
		{
			"frame_index": 357,
			"centroid": [
				107,
				558
			],
			"gender": [
				"U",
				-1
			],
			"age": [
				-1,
				-1
			],
			"mood": [
				-1,
				-1
			],
			"employee": [
				0,
				0.0036719706242350062
			]
		},
		{
			"frame_index": 358,
			"centroid": [
				108,
				555
			],
			"gender": [
				"U",
				-1
			],
			"age": [
				-1,
				-1
			],
			"mood": [
				-1,
				-1
			],
			"employee": [
				0,
				0.0004630344188918043
			]
		},
		{
			"frame_index": 359,
			"centroid": [
				110,
				552
			],
			"gender": [
				"U",
				-1
			],
			"age": [
				-1,
				-1
			],
			"mood": [
				-1,
				-1
			],
			"employee": [
				0,
				0.0017085904129093498
			]
		},
		{
			"frame_index": 360,
			"centroid": [
				109,
				548
			],
			"gender": [
				"U",
				-1
			],
			"age": [
				-1,
				-1
			],
			"mood": [
				-1,
				-1
			],
			"employee": [
				0,
				0.0
			]
		},
		{
			"frame_index": 361,
			"centroid": [
				111,
				547
			],
			"gender": [
				"U",
				-1
			],
			"age": [
				-1,
				-1
			],
			"mood": [
				-1,
				-1
			],
			"employee": [
				0,
				0.007975986277873071
			]
		},
		{
			"frame_index": 362,
			"centroid": [
				129,
				542
			],
			"gender": [
				"U",
				-1
			],
			"age": [
				-1,
				-1
			],
			"mood": [
				-1,
				-1
			],
			"employee": [
				0,
				0.001039100985221675
			]
		},
		{
			"frame_index": 363,
			"centroid": [
				135,
				538
			],
			"gender": [
				"U",
				-1
			],
			"age": [
				-1,
				-1
			],
			"mood": [
				-1,
				-1
			],
			"employee": [
				0,
				0.0011218727796267903
			]
		},
		{
			"frame_index": 364,
			"centroid": [
				141,
				538
			],
			"gender": [
				"U",
				-1
			],
			"age": [
				-1,
				-1
			],
			"mood": [
				-1,
				-1
			],
			"employee": [
				0,
				0.00033108928374351616
			]
		},
		{
			"frame_index": 365,
			"centroid": [
				133,
				533
			],
			"gender": [
				"U",
				-1
			],
			"age": [
				-1,
				-1
			],
			"mood": [
				-1,
				-1
			],
			"employee": [
				0,
				0.001814283358073561
			]
		},
		{
			"frame_index": 366,
			"centroid": [
				132,
				531
			],
			"gender": [
				"U",
				-1
			],
			"age": [
				-1,
				-1
			],
			"mood": [
				-1,
				-1
			],
			"employee": [
				0,
				0.0123342175066313
			]
		},
		{
			"frame_index": 367,
			"centroid": [
				138,
				523
			],
			"gender": [
				"U",
				-1
			],
			"age": [
				-1,
				-1
			],
			"mood": [
				-1,
				-1
			],
			"employee": [
				0,
				0.019405513630063143
			]
		},
		{
			"frame_index": 368,
			"centroid": [
				142,
				519
			],
			"gender": [
				"U",
				-1
			],
			"age": [
				-1,
				-1
			],
			"mood": [
				-1,
				-1
			],
			"employee": [
				0,
				0.016381236038719285
			]
		},
		{
			"frame_index": 369,
			"centroid": [
				141,
				514
			],
			"gender": [
				"U",
				-1
			],
			"age": [
				-1,
				-1
			],
			"mood": [
				-1,
				-1
			],
			"employee": [
				0,
				0.021037274096385544
			]
		},
		{
			"frame_index": 370,
			"centroid": [
				152,
				510
			],
			"gender": [
				"U",
				-1
			],
			"age": [
				-1,
				-1
			],
			"mood": [
				-1,
				-1
			],
			"employee": [
				0,
				0.02086894586894587
			]
		},
		{
			"frame_index": 371,
			"centroid": [
				153,
				506
			],
			"gender": [
				"U",
				-1
			],
			"age": [
				-1,
				-1
			],
			"mood": [
				-1,
				-1
			],
			"employee": [
				0,
				0.031181775035595632
			]
		},
		{
			"frame_index": 372,
			"centroid": [
				156,
				506
			],
			"gender": [
				"U",
				-1
			],
			"age": [
				-1,
				-1
			],
			"mood": [
				-1,
				-1
			],
			"employee": [
				0,
				0.036621737220539616
			]
		},
		{
			"frame_index": 373,
			"centroid": [
				180,
				502
			],
			"gender": [
				"U",
				-1
			],
			"age": [
				-1,
				-1
			],
			"mood": [
				-1,
				-1
			],
			"employee": [
				0,
				0.039698937426210154
			]
		},
		{
			"frame_index": 374,
			"centroid": [
				186,
				499
			],
			"gender": [
				"U",
				-1
			],
			"age": [
				-1,
				-1
			],
			"mood": [
				-1,
				-1
			],
			"employee": [
				0,
				0.051754819574888776
			]
		},
		{
			"frame_index": 375,
			"centroid": [
				191,
				495
			],
			"gender": [
				"U",
				-1
			],
			"age": [
				-1,
				-1
			],
			"mood": [
				-1,
				-1
			],
			"employee": [
				0,
				0.047032967032967034
			]
		},
		{
			"frame_index": 376,
			"centroid": [
				196,
				493
			],
			"gender": [
				"U",
				-1
			],
			"age": [
				-1,
				-1
			],
			"mood": [
				-1,
				-1
			],
			"employee": [
				0,
				0.03666658534800322
			]
		},
		{
			"frame_index": 377,
			"centroid": [
				198,
				485
			],
			"gender": [
				"U",
				-1
			],
			"age": [
				-1,
				-1
			],
			"mood": [
				-1,
				-1
			],
			"employee": [
				0,
				0.03886168910648715
			]
		},
		{
			"frame_index": 378,
			"centroid": [
				195,
				484
			],
			"gender": [
				"U",
				-1
			],
			"age": [
				-1,
				-1
			],
			"mood": [
				-1,
				-1
			],
			"employee": [
				0,
				0.03790730572805524
			]
		},
		{
			"frame_index": 379,
			"centroid": [
				196,
				478
			],
			"gender": [
				"U",
				-1
			],
			"age": [
				-1,
				-1
			],
			"mood": [
				-1,
				-1
			],
			"employee": [
				0,
				0.03983918128654971
			]
		},
		{
			"frame_index": 380,
			"centroid": [
				195,
				471
			],
			"gender": [
				"U",
				-1
			],
			"age": [
				-1,
				-1
			],
			"mood": [
				-1,
				-1
			],
			"employee": [
				0,
				0.043648053339683295
			]
		},
		{
			"frame_index": 381,
			"centroid": [
				201,
				466
			],
			"gender": [
				"U",
				-1
			],
			"age": [
				-1,
				-1
			],
			"mood": [
				-1,
				-1
			],
			"employee": [
				0,
				0.05533364661654135
			]
		},
		{
			"frame_index": 382,
			"centroid": [
				199,
				464
			],
			"gender": [
				"U",
				-1
			],
			"age": [
				-1,
				-1
			],
			"mood": [
				-1,
				-1
			],
			"employee": [
				0,
				0.050515463917525774
			]
		},
		{
			"frame_index": 383,
			"centroid": [
				199,
				461
			],
			"gender": [
				"U",
				-1
			],
			"age": [
				-1,
				-1
			],
			"mood": [
				-1,
				-1
			],
			"employee": [
				0,
				0.05670585092172054
			]
		},
		{
			"frame_index": 384,
			"centroid": [
				202,
				451
			],
			"gender": [
				"U",
				-1
			],
			"age": [
				-1,
				-1
			],
			"mood": [
				-1,
				-1
			],
			"employee": [
				0,
				0.05735683417426522
			]
		},
		{
			"frame_index": 385,
			"centroid": [
				207,
				443
			],
			"gender": [
				"U",
				-1
			],
			"age": [
				-1,
				-1
			],
			"mood": [
				-1,
				-1
			],
			"employee": [
				0,
				0.04976086956521739
			]
		},
		{
			"frame_index": 386,
			"centroid": [
				206,
				441
			],
			"gender": [
				"U",
				-1
			],
			"age": [
				-1,
				-1
			],
			"mood": [
				-1,
				-1
			],
			"employee": [
				0,
				0.04527226677923174
			]
		},
		{
			"frame_index": 387,
			"centroid": [
				206,
				435
			],
			"gender": [
				"U",
				-1
			],
			"age": [
				-1,
				-1
			],
			"mood": [
				-1,
				-1
			],
			"employee": [
				0,
				0.04735320106032613
			]
		},
		{
			"frame_index": 388,
			"centroid": [
				213,
				431
			],
			"gender": [
				"U",
				-1
			],
			"age": [
				-1,
				-1
			],
			"mood": [
				-1,
				-1
			],
			"employee": [
				0,
				0.05426998385561121
			]
		},
		{
			"frame_index": 389,
			"centroid": [
				214,
				429
			],
			"gender": [
				"U",
				-1
			],
			"age": [
				-1,
				-1
			],
			"mood": [
				-1,
				-1
			],
			"employee": [
				0,
				0.050360710321864594
			]
		},
		{
			"frame_index": 390,
			"centroid": [
				219,
				424
			],
			"gender": [
				"U",
				-1
			],
			"age": [
				-1,
				-1
			],
			"mood": [
				-1,
				-1
			],
			"employee": [
				0,
				0.05628087508821454
			]
		},
		{
			"frame_index": 391,
			"centroid": [
				229,
				414
			],
			"gender": [
				"U",
				-1
			],
			"age": [
				-1,
				-1
			],
			"mood": [
				-1,
				-1
			],
			"employee": [
				0,
				0.06971112999150382
			]
		},
		{
			"frame_index": 392,
			"centroid": [
				236,
				406
			],
			"gender": [
				"U",
				-1
			],
			"age": [
				-1,
				-1
			],
			"mood": [
				-1,
				-1
			],
			"employee": [
				0,
				0.05985572236303373
			]
		},
		{
			"frame_index": 393,
			"centroid": [
				236,
				401
			],
			"gender": [
				"U",
				-1
			],
			"age": [
				-1,
				-1
			],
			"mood": [
				-1,
				-1
			],
			"employee": [
				0,
				0.057630670611439845
			]
		},
		{
			"frame_index": 394,
			"centroid": [
				242,
				390
			],
			"gender": [
				"U",
				-1
			],
			"age": [
				-1,
				-1
			],
			"mood": [
				-1,
				-1
			],
			"employee": [
				0,
				0.061606734973569145
			]
		},
		{
			"frame_index": 395,
			"centroid": [
				244,
				384
			],
			"gender": [
				"U",
				-1
			],
			"age": [
				-1,
				-1
			],
			"mood": [
				-1,
				-1
			],
			"employee": [
				0,
				0.06633728590250329
			]
		},
		{
			"frame_index": 396,
			"centroid": [
				250,
				378
			],
			"gender": [
				"U",
				-1
			],
			"age": [
				-1,
				-1
			],
			"mood": [
				-1,
				-1
			],
			"employee": [
				0,
				0.06007192647515873
			]
		},
		{
			"frame_index": 397,
			"centroid": [
				253,
				372
			],
			"gender": [
				"U",
				-1
			],
			"age": [
				-1,
				-1
			],
			"mood": [
				-1,
				-1
			],
			"employee": [
				0,
				0.05593809430126566
			]
		},
		{
			"frame_index": 398,
			"centroid": [
				260,
				363
			],
			"gender": [
				"U",
				-1
			],
			"age": [
				-1,
				-1
			],
			"mood": [
				-1,
				-1
			],
			"employee": [
				0,
				0.05083775185577943
			]
		},
		{
			"frame_index": 399,
			"centroid": [
				263,
				362
			],
			"gender": [
				"U",
				-1
			],
			"age": [
				-1,
				-1
			],
			"mood": [
				-1,
				-1
			],
			"employee": [
				0,
				0.0687254699442264
			]
		},
		{
			"frame_index": 400,
			"centroid": [
				271,
				353
			],
			"gender": [
				"U",
				-1
			],
			"age": [
				-1,
				-1
			],
			"mood": [
				-1,
				-1
			],
			"employee": [
				0,
				0.05408994732814118
			]
		},
		{
			"frame_index": 401,
			"centroid": [
				272,
				345
			],
			"gender": [
				"U",
				-1
			],
			"age": [
				-1,
				-1
			],
			"mood": [
				-1,
				-1
			],
			"employee": [
				0,
				0.05546655987184622
			]
		},
		{
			"frame_index": 402,
			"centroid": [
				273,
				339
			],
			"gender": [
				"U",
				-1
			],
			"age": [
				-1,
				-1
			],
			"mood": [
				-1,
				-1
			],
			"employee": [
				0,
				0.04841464482788824
			]
		},
		{
			"frame_index": 403,
			"centroid": [
				274,
				332
			],
			"gender": [
				"U",
				-1
			],
			"age": [
				-1,
				-1
			],
			"mood": [
				-1,
				-1
			],
			"employee": [
				0,
				0.049623567921440265
			]
		},
		{
			"frame_index": 404,
			"centroid": [
				276,
				335
			],
			"gender": [
				"U",
				-1
			],
			"age": [
				-1,
				-1
			],
			"mood": [
				-1,
				-1
			],
			"employee": [
				0,
				0.06811940298507463
			]
		},
		{
			"frame_index": 405,
			"centroid": [
				277,
				330
			],
			"gender": [
				"U",
				-1
			],
			"age": [
				-1,
				-1
			],
			"mood": [
				-1,
				-1
			],
			"employee": [
				0,
				0.06523655598001764
			]
		},
		{
			"frame_index": 406,
			"centroid": [
				278,
				329
			],
			"gender": [
				"U",
				-1
			],
			"age": [
				-1,
				-1
			],
			"mood": [
				-1,
				-1
			],
			"employee": [
				0,
				0.0696157495256167
			]
		},
		{
			"frame_index": 407,
			"centroid": [
				285,
				320
			],
			"gender": [
				"U",
				-1
			],
			"age": [
				-1,
				-1
			],
			"mood": [
				-1,
				-1
			],
			"employee": [
				0,
				0.06042848141146818
			]
		},
		{
			"frame_index": 408,
			"centroid": [
				286,
				318
			],
			"gender": [
				"U",
				-1
			],
			"age": [
				-1,
				-1
			],
			"mood": [
				-1,
				-1
			],
			"employee": [
				0,
				0.06989811670268602
			]
		},
		{
			"frame_index": 409,
			"centroid": [
				287,
				313
			],
			"gender": [
				"U",
				-1
			],
			"age": [
				-1,
				-1
			],
			"mood": [
				-1,
				-1
			],
			"employee": [
				0,
				0.06827948432277574
			]
		},
		{
			"frame_index": 410,
			"centroid": [
				286,
				301
			],
			"gender": [
				"U",
				-1
			],
			"age": [
				-1,
				-1
			],
			"mood": [
				-1,
				-1
			],
			"employee": [
				0,
				0.05422255809559796
			]
		},
		{
			"frame_index": 411,
			"centroid": [
				288,
				296
			],
			"gender": [
				"U",
				-1
			],
			"age": [
				-1,
				-1
			],
			"mood": [
				-1,
				-1
			],
			"employee": [
				0,
				0.052384108703757405
			]
		},
		{
			"frame_index": 412,
			"centroid": [
				288,
				293
			],
			"gender": [
				"U",
				-1
			],
			"age": [
				-1,
				-1
			],
			"mood": [
				-1,
				-1
			],
			"employee": [
				0,
				0.05131929314935851
			]
		},
		{
			"frame_index": 413,
			"centroid": [
				290,
				283
			],
			"gender": [
				"U",
				-1
			],
			"age": [
				-1,
				-1
			],
			"mood": [
				-1,
				-1
			],
			"employee": [
				0,
				0.044553233503373375
			]
		},
		{
			"frame_index": 414,
			"centroid": [
				291,
				273
			],
			"gender": [
				"U",
				-1
			],
			"age": [
				-1,
				-1
			],
			"mood": [
				-1,
				-1
			],
			"employee": [
				0,
				0.04261061946902655
			]
		},
		{
			"frame_index": 415,
			"centroid": [
				293,
				275
			],
			"gender": [
				"U",
				-1
			],
			"age": [
				-1,
				-1
			],
			"mood": [
				-1,
				-1
			],
			"employee": [
				0,
				0.049701633165829144
			]
		},
		{
			"frame_index": 416,
			"centroid": [
				292,
				275
			],
			"gender": [
				"U",
				-1
			],
			"age": [
				-1,
				-1
			],
			"mood": [
				-1,
				-1
			],
			"employee": [
				0,
				0.06737342898349848
			]
		},
		{
			"frame_index": 417,
			"centroid": [
				299,
				264
			],
			"gender": [
				"U",
				-1
			],
			"age": [
				-1,
				-1
			],
			"mood": [
				-1,
				-1
			],
			"employee": [
				0,
				0.05424616535727647
			]
		},
		{
			"frame_index": 418,
			"centroid": [
				299,
				257
			],
			"gender": [
				"U",
				-1
			],
			"age": [
				-1,
				-1
			],
			"mood": [
				-1,
				-1
			],
			"employee": [
				0,
				0.045464372189553785
			]
		},
		{
			"frame_index": 419,
			"centroid": [
				302,
				254
			],
			"gender": [
				"U",
				-1
			],
			"age": [
				-1,
				-1
			],
			"mood": [
				-1,
				-1
			],
			"employee": [
				0,
				0.04790380658436214
			]
		},
		{
			"frame_index": 420,
			"centroid": [
				302,
				253
			],
			"gender": [
				"U",
				-1
			],
			"age": [
				-1,
				-1
			],
			"mood": [
				-1,
				-1
			],
			"employee": [
				0,
				0.08897800365282299
			]
		},
		{
			"frame_index": 421,
			"centroid": [
				305,
				245
			],
			"gender": [
				"U",
				-1
			],
			"age": [
				-1,
				-1
			],
			"mood": [
				-1,
				-1
			],
			"employee": [
				0,
				0.08843751971235728
			]
		},
		{
			"frame_index": 422,
			"centroid": [
				306,
				235
			],
			"gender": [
				"U",
				-1
			],
			"age": [
				-1,
				-1
			],
			"mood": [
				-1,
				-1
			],
			"employee": [
				0,
				0.06962566844919786
			]
		},
		{
			"frame_index": 423,
			"centroid": [
				312,
				219
			],
			"gender": [
				"U",
				-1
			],
			"age": [
				-1,
				-1
			],
			"mood": [
				-1,
				-1
			],
			"employee": [
				0,
				0.05884734782021865
			]
		},
		{
			"frame_index": 424,
			"centroid": [
				310,
				216
			],
			"gender": [
				"U",
				-1
			],
			"age": [
				-1,
				-1
			],
			"mood": [
				-1,
				-1
			],
			"employee": [
				0,
				0.08666046354254779
			]
		},
		{
			"frame_index": 425,
			"centroid": [
				310,
				216
			],
			"gender": [
				"U",
				-1
			],
			"age": [
				-1,
				-1
			],
			"mood": [
				-1,
				-1
			],
			"employee": [
				0,
				0.08124058262179809
			]
		},
		{
			"frame_index": 426,
			"centroid": [
				311,
				208
			],
			"gender": [
				"U",
				-1
			],
			"age": [
				-1,
				-1
			],
			"mood": [
				-1,
				-1
			],
			"employee": [
				0,
				0.08016552574233453
			]
		},
		{
			"frame_index": 427,
			"centroid": [
				311,
				221
			],
			"gender": [
				"U",
				-1
			],
			"age": [
				-1,
				-1
			],
			"mood": [
				-1,
				-1
			],
			"employee": [
				0,
				0.09981840193704601
			]
		},
		{
			"frame_index": 428,
			"centroid": [
				311,
				211
			],
			"gender": [
				"U",
				-1
			],
			"age": [
				-1,
				-1
			],
			"mood": [
				-1,
				-1
			],
			"employee": [
				0,
				0.09552435371837628
			]
		},
		{
			"frame_index": 429,
			"centroid": [
				313,
				211
			],
			"gender": [
				"U",
				-1
			],
			"age": [
				-1,
				-1
			],
			"mood": [
				-1,
				-1
			],
			"employee": [
				0,
				0.1004266283686745
			]
		},
		{
			"frame_index": 430,
			"centroid": [
				313,
				205
			],
			"gender": [
				"U",
				-1
			],
			"age": [
				-1,
				-1
			],
			"mood": [
				-1,
				-1
			],
			"employee": [
				0,
				0.09077966101694915
			]
		},
		{
			"frame_index": 431,
			"centroid": [
				313,
				207
			],
			"gender": [
				"U",
				-1
			],
			"age": [
				-1,
				-1
			],
			"mood": [
				-1,
				-1
			],
			"employee": [
				0,
				0.08378737541528239
			]
		},
		{
			"frame_index": 432,
			"centroid": [
				311,
				197
			],
			"gender": [
				"U",
				-1
			],
			"age": [
				-1,
				-1
			],
			"mood": [
				-1,
				-1
			],
			"employee": [
				0,
				0.07672176308539945
			]
		},
		{
			"frame_index": 433,
			"centroid": [
				311,
				189
			],
			"gender": [
				"U",
				-1
			],
			"age": [
				-1,
				-1
			],
			"mood": [
				-1,
				-1
			],
			"employee": [
				0,
				0.07186234817813765
			]
		},
		{
			"frame_index": 434,
			"centroid": [
				313,
				194
			],
			"gender": [
				"U",
				-1
			],
			"age": [
				-1,
				-1
			],
			"mood": [
				-1,
				-1
			],
			"employee": [
				0,
				0.09979253112033196
			]
		},
		{
			"frame_index": 435,
			"centroid": [
				321,
				178
			],
			"gender": [
				"U",
				-1
			],
			"age": [
				-1,
				-1
			],
			"mood": [
				-1,
				-1
			],
			"employee": [
				0,
				0.09566995643282653
			]
		},
		{
			"frame_index": 436,
			"centroid": [
				323,
				175
			],
			"gender": [
				"U",
				-1
			],
			"age": [
				-1,
				-1
			],
			"mood": [
				-1,
				-1
			],
			"employee": [
				0,
				0.10505767524401065
			]
		},
		{
			"frame_index": 437,
			"centroid": [
				324,
				171
			],
			"gender": [
				"U",
				-1
			],
			"age": [
				-1,
				-1
			],
			"mood": [
				-1,
				-1
			],
			"employee": [
				0,
				0.0919074624178594
			]
		},
		{
			"frame_index": 438,
			"centroid": [
				325,
				169
			],
			"gender": [
				"U",
				-1
			],
			"age": [
				-1,
				-1
			],
			"mood": [
				-1,
				-1
			],
			"employee": [
				0,
				0.0868653723452739
			]
		},
		{
			"frame_index": 439,
			"centroid": [
				311,
				168
			],
			"gender": [
				"U",
				-1
			],
			"age": [
				-1,
				-1
			],
			"mood": [
				-1,
				-1
			],
			"employee": [
				0,
				0.09316770186335403
			]
		},
		{
			"frame_index": 440,
			"centroid": [
				314,
				168
			],
			"gender": [
				"U",
				-1
			],
			"age": [
				-1,
				-1
			],
			"mood": [
				-1,
				-1
			],
			"employee": [
				0,
				0.08102736584620089
			]
		},
		{
			"frame_index": 441,
			"centroid": [
				317,
				167
			],
			"gender": [
				"U",
				-1
			],
			"age": [
				-1,
				-1
			],
			"mood": [
				-1,
				-1
			],
			"employee": [
				0,
				0.08858695652173913
			]
		},
		{
			"frame_index": 442,
			"centroid": [
				316,
				166
			],
			"gender": [
				"U",
				-1
			],
			"age": [
				-1,
				-1
			],
			"mood": [
				-1,
				-1
			],
			"employee": [
				0,
				0.08462732919254658
			]
		},
		{
			"frame_index": 443,
			"centroid": [
				311,
				165
			],
			"gender": [
				"U",
				-1
			],
			"age": [
				-1,
				-1
			],
			"mood": [
				-1,
				-1
			],
			"employee": [
				0,
				0.07693426410703898
			]
		},
		{
			"frame_index": 444,
			"centroid": [
				313,
				165
			],
			"gender": [
				"U",
				-1
			],
			"age": [
				-1,
				-1
			],
			"mood": [
				-1,
				-1
			],
			"employee": [
				0,
				0.07784992784992785
			]
		},
		{
			"frame_index": 445,
			"centroid": [
				316,
				157
			],
			"gender": [
				"U",
				-1
			],
			"age": [
				-1,
				-1
			],
			"mood": [
				-1,
				-1
			],
			"employee": [
				0,
				0.06854895350470572
			]
		},
		{
			"frame_index": 446,
			"centroid": [
				316,
				152
			],
			"gender": [
				"U",
				-1
			],
			"age": [
				-1,
				-1
			],
			"mood": [
				-1,
				-1
			],
			"employee": [
				0,
				0.07409326424870466
			]
		},
		{
			"frame_index": 447,
			"centroid": [
				323,
				142
			],
			"gender": [
				"U",
				-1
			],
			"age": [
				-1,
				-1
			],
			"mood": [
				-1,
				-1
			],
			"employee": [
				0,
				0.07268647582783709
			]
		},
		{
			"frame_index": 448,
			"centroid": [
				319,
				141
			],
			"gender": [
				"U",
				-1
			],
			"age": [
				-1,
				-1
			],
			"mood": [
				-1,
				-1
			],
			"employee": [
				0,
				0.07350777301516218
			]
		},
		{
			"frame_index": 449,
			"centroid": [
				328,
				138
			],
			"gender": [
				"U",
				-1
			],
			"age": [
				-1,
				-1
			],
			"mood": [
				-1,
				-1
			],
			"employee": [
				0,
				0.06895638938521607
			]
		},
		{
			"frame_index": 450,
			"centroid": [
				334,
				131
			],
			"gender": [
				"U",
				-1
			],
			"age": [
				-1,
				-1
			],
			"mood": [
				-1,
				-1
			],
			"employee": [
				0,
				0.07025211630474788
			]
		},
		{
			"frame_index": 451,
			"centroid": [
				345,
				125
			],
			"gender": [
				"U",
				-1
			],
			"age": [
				-1,
				-1
			],
			"mood": [
				-1,
				-1
			],
			"employee": [
				0,
				0.05055217060167555
			]
		},
		{
			"frame_index": 452,
			"centroid": [
				354,
				121
			],
			"gender": [
				"U",
				-1
			],
			"age": [
				-1,
				-1
			],
			"mood": [
				-1,
				-1
			],
			"employee": [
				0,
				0.029922338967565097
			]
		},
		{
			"frame_index": 453,
			"centroid": [
				353,
				119
			],
			"gender": [
				"U",
				-1
			],
			"age": [
				-1,
				-1
			],
			"mood": [
				-1,
				-1
			],
			"employee": [
				0,
				0.04626581181770924
			]
		},
		{
			"frame_index": 454,
			"centroid": [
				355,
				119
			],
			"gender": [
				"U",
				-1
			],
			"age": [
				-1,
				-1
			],
			"mood": [
				-1,
				-1
			],
			"employee": [
				0,
				0.06190817790530846
			]
		},
		{
			"frame_index": 455,
			"centroid": [
				354,
				110
			],
			"gender": [
				"U",
				-1
			],
			"age": [
				-1,
				-1
			],
			"mood": [
				-1,
				-1
			],
			"employee": [
				0,
				0.046097650066967005
			]
		},
		{
			"frame_index": 456,
			"centroid": [
				354,
				113
			],
			"gender": [
				"U",
				-1
			],
			"age": [
				-1,
				-1
			],
			"mood": [
				-1,
				-1
			],
			"employee": [
				0,
				0.04846515486725664
			]
		},
		{
			"frame_index": 457,
			"centroid": [
				359,
				113
			],
			"gender": [
				"U",
				-1
			],
			"age": [
				-1,
				-1
			],
			"mood": [
				-1,
				-1
			],
			"employee": [
				0,
				0.05277681959296309
			]
		},
		{
			"frame_index": 458,
			"centroid": [
				366,
				112
			],
			"gender": [
				"U",
				-1
			],
			"age": [
				-1,
				-1
			],
			"mood": [
				-1,
				-1
			],
			"employee": [
				0,
				0.042736757624398075
			]
		},
		{
			"frame_index": 459,
			"centroid": [
				375,
				112
			],
			"gender": [
				"U",
				-1
			],
			"age": [
				-1,
				-1
			],
			"mood": [
				-1,
				-1
			],
			"employee": [
				0,
				0.04807259637018149
			]
		},
		{
			"frame_index": 460,
			"centroid": [
				379,
				112
			],
			"gender": [
				"U",
				-1
			],
			"age": [
				-1,
				-1
			],
			"mood": [
				-1,
				-1
			],
			"employee": [
				0,
				0.043791701817624054
			]
		},
		{
			"frame_index": 461,
			"centroid": [
				380,
				111
			],
			"gender": [
				"U",
				-1
			],
			"age": [
				-1,
				-1
			],
			"mood": [
				-1,
				-1
			],
			"employee": [
				0,
				0.04244126659856997
			]
		},
		{
			"frame_index": 462,
			"centroid": [
				384,
				113
			],
			"gender": [
				"U",
				-1
			],
			"age": [
				-1,
				-1
			],
			"mood": [
				-1,
				-1
			],
			"employee": [
				0,
				0.05257612745727869
			]
		},
		{
			"frame_index": 463,
			"centroid": [
				389,
				113
			],
			"gender": [
				"U",
				-1
			],
			"age": [
				-1,
				-1
			],
			"mood": [
				-1,
				-1
			],
			"employee": [
				0,
				0.051729559748427675
			]
		},
		{
			"frame_index": 464,
			"centroid": [
				389,
				111
			],
			"gender": [
				"U",
				-1
			],
			"age": [
				-1,
				-1
			],
			"mood": [
				-1,
				-1
			],
			"employee": [
				0,
				0.036477495107632096
			]
		},
		{
			"frame_index": 465,
			"centroid": [
				394,
				111
			],
			"gender": [
				"U",
				-1
			],
			"age": [
				-1,
				-1
			],
			"mood": [
				-1,
				-1
			],
			"employee": [
				0,
				0.0416644912024226
			]
		},
		{
			"frame_index": 466,
			"centroid": [
				392,
				110
			],
			"gender": [
				"U",
				-1
			],
			"age": [
				-1,
				-1
			],
			"mood": [
				-1,
				-1
			],
			"employee": [
				0,
				0.028238182934315532
			]
		},
		{
			"frame_index": 467,
			"centroid": [
				397,
				110
			],
			"gender": [
				"U",
				-1
			],
			"age": [
				-1,
				-1
			],
			"mood": [
				-1,
				-1
			],
			"employee": [
				0,
				0.034442109579211726
			]
		},
		{
			"frame_index": 468,
			"centroid": [
				398,
				109
			],
			"gender": [
				"U",
				-1
			],
			"age": [
				-1,
				-1
			],
			"mood": [
				-1,
				-1
			],
			"employee": [
				0,
				0.036553724053724056
			]
		},
		{
			"frame_index": 469,
			"centroid": [
				405,
				109
			],
			"gender": [
				"U",
				-1
			],
			"age": [
				-1,
				-1
			],
			"mood": [
				-1,
				-1
			],
			"employee": [
				0,
				0.044219219219219216
			]
		},
		{
			"frame_index": 470,
			"centroid": [
				406,
				109
			],
			"gender": [
				"U",
				-1
			],
			"age": [
				-1,
				-1
			],
			"mood": [
				-1,
				-1
			],
			"employee": [
				0,
				0.04318181818181818
			]
		},
		{
			"frame_index": 471,
			"centroid": [
				397,
				110
			],
			"gender": [
				"U",
				-1
			],
			"age": [
				-1,
				-1
			],
			"mood": [
				-1,
				-1
			],
			"employee": [
				0,
				0.04205751984331512
			]
		},
		{
			"frame_index": 472,
			"centroid": [
				396,
				109
			],
			"gender": [
				"U",
				-1
			],
			"age": [
				-1,
				-1
			],
			"mood": [
				-1,
				-1
			],
			"employee": [
				0,
				0.029712260216847374
			]
		},
		{
			"frame_index": 473,
			"centroid": [
				394,
				110
			],
			"gender": [
				"U",
				-1
			],
			"age": [
				-1,
				-1
			],
			"mood": [
				-1,
				-1
			],
			"employee": [
				0,
				0.028792997542997543
			]
		},
		{
			"frame_index": 474,
			"centroid": [
				393,
				111
			],
			"gender": [
				"U",
				-1
			],
			"age": [
				-1,
				-1
			],
			"mood": [
				-1,
				-1
			],
			"employee": [
				0,
				0.03230219654936536
			]
		},
		{
			"frame_index": 475,
			"centroid": [
				392,
				110
			],
			"gender": [
				"U",
				-1
			],
			"age": [
				-1,
				-1
			],
			"mood": [
				-1,
				-1
			],
			"employee": [
				0,
				0.02340959185224595
			]
		},
		{
			"frame_index": 476,
			"centroid": [
				395,
				109
			],
			"gender": [
				"U",
				-1
			],
			"age": [
				-1,
				-1
			],
			"mood": [
				-1,
				-1
			],
			"employee": [
				0,
				0.026343759489826906
			]
		},
		{
			"frame_index": 477,
			"centroid": [
				394,
				107
			],
			"gender": [
				"U",
				-1
			],
			"age": [
				-1,
				-1
			],
			"mood": [
				-1,
				-1
			],
			"employee": [
				0,
				0.03140356265356265
			]
		},
		{
			"frame_index": 478,
			"centroid": [
				393,
				107
			],
			"gender": [
				"U",
				-1
			],
			"age": [
				-1,
				-1
			],
			"mood": [
				-1,
				-1
			],
			"employee": [
				0,
				0.03103342845495312
			]
		},
		{
			"frame_index": 479,
			"centroid": [
				393,
				108
			],
			"gender": [
				"U",
				-1
			],
			"age": [
				-1,
				-1
			],
			"mood": [
				-1,
				-1
			],
			"employee": [
				0,
				0.02922529766506881
			]
		},
		{
			"frame_index": 480,
			"centroid": [
				389,
				108
			],
			"gender": [
				"U",
				-1
			],
			"age": [
				-1,
				-1
			],
			"mood": [
				-1,
				-1
			],
			"employee": [
				0,
				0.03322333883305835
			]
		},
		{
			"frame_index": 481,
			"centroid": [
				390,
				107
			],
			"gender": [
				"U",
				-1
			],
			"age": [
				-1,
				-1
			],
			"mood": [
				-1,
				-1
			],
			"employee": [
				0,
				0.033292978208232446
			]
		},
		{
			"frame_index": 482,
			"centroid": [
				387,
				108
			],
			"gender": [
				"U",
				-1
			],
			"age": [
				-1,
				-1
			],
			"mood": [
				-1,
				-1
			],
			"employee": [
				0,
				0.03777032438926712
			]
		},
		{
			"frame_index": 483,
			"centroid": [
				386,
				109
			],
			"gender": [
				"U",
				-1
			],
			"age": [
				-1,
				-1
			],
			"mood": [
				-1,
				-1
			],
			"employee": [
				0,
				0.03905547226386807
			]
		},
		{
			"frame_index": 484,
			"centroid": [
				388,
				108
			],
			"gender": [
				"U",
				-1
			],
			"age": [
				-1,
				-1
			],
			"mood": [
				-1,
				-1
			],
			"employee": [
				0,
				0.04065265486725664
			]
		},
		{
			"frame_index": 485,
			"centroid": [
				387,
				108
			],
			"gender": [
				"U",
				-1
			],
			"age": [
				-1,
				-1
			],
			"mood": [
				-1,
				-1
			],
			"employee": [
				0,
				0.04241021429104756
			]
		},
		{
			"frame_index": 486,
			"centroid": [
				387,
				108
			],
			"gender": [
				"U",
				-1
			],
			"age": [
				-1,
				-1
			],
			"mood": [
				-1,
				-1
			],
			"employee": [
				0,
				0.038602254909280966
			]
		},
		{
			"frame_index": 487,
			"centroid": [
				388,
				108
			],
			"gender": [
				"U",
				-1
			],
			"age": [
				-1,
				-1
			],
			"mood": [
				-1,
				-1
			],
			"employee": [
				0,
				0.04564833872390473
			]
		},
		{
			"frame_index": 488,
			"centroid": [
				388,
				109
			],
			"gender": [
				"U",
				-1
			],
			"age": [
				-1,
				-1
			],
			"mood": [
				-1,
				-1
			],
			"employee": [
				0,
				0.0407612730782557
			]
		},
		{
			"frame_index": 489,
			"centroid": [
				388,
				108
			],
			"gender": [
				"U",
				-1
			],
			"age": [
				-1,
				-1
			],
			"mood": [
				-1,
				-1
			],
			"employee": [
				0,
				0.04826815642458101
			]
		},
		{
			"frame_index": 490,
			"centroid": [
				389,
				108
			],
			"gender": [
				"U",
				-1
			],
			"age": [
				-1,
				-1
			],
			"mood": [
				-1,
				-1
			],
			"employee": [
				0,
				0.030326062172227712
			]
		},
		{
			"frame_index": 491,
			"centroid": [
				391,
				107
			],
			"gender": [
				"U",
				-1
			],
			"age": [
				-1,
				-1
			],
			"mood": [
				-1,
				-1
			],
			"employee": [
				0,
				0.024397659040814774
			]
		},
		{
			"frame_index": 492,
			"centroid": [
				392,
				107
			],
			"gender": [
				"U",
				-1
			],
			"age": [
				-1,
				-1
			],
			"mood": [
				-1,
				-1
			],
			"employee": [
				0,
				0.018916464891041162
			]
		},
		{
			"frame_index": 493,
			"centroid": [
				391,
				107
			],
			"gender": [
				"U",
				-1
			],
			"age": [
				-1,
				-1
			],
			"mood": [
				-1,
				-1
			],
			"employee": [
				0,
				0.01635752140236445
			]
		},
		{
			"frame_index": 494,
			"centroid": [
				391,
				107
			],
			"gender": [
				"U",
				-1
			],
			"age": [
				-1,
				-1
			],
			"mood": [
				-1,
				-1
			],
			"employee": [
				0,
				0.018192009783938035
			]
		},
		{
			"frame_index": 495,
			"centroid": [
				390,
				106
			],
			"gender": [
				"U",
				-1
			],
			"age": [
				-1,
				-1
			],
			"mood": [
				-1,
				-1
			],
			"employee": [
				0,
				0.017295238095238096
			]
		},
		{
			"frame_index": 496,
			"centroid": [
				391,
				107
			],
			"gender": [
				"U",
				-1
			],
			"age": [
				-1,
				-1
			],
			"mood": [
				-1,
				-1
			],
			"employee": [
				0,
				0.01806122448979592
			]
		},
		{
			"frame_index": 497,
			"centroid": [
				391,
				108
			],
			"gender": [
				"U",
				-1
			],
			"age": [
				-1,
				-1
			],
			"mood": [
				-1,
				-1
			],
			"employee": [
				0,
				0.01816916653780733
			]
		},
		{
			"frame_index": 498,
			"centroid": [
				392,
				108
			],
			"gender": [
				"U",
				-1
			],
			"age": [
				-1,
				-1
			],
			"mood": [
				-1,
				-1
			],
			"employee": [
				0,
				0.017911595131326074
			]
		},
		{
			"frame_index": 499,
			"centroid": [
				392,
				108
			],
			"gender": [
				"U",
				-1
			],
			"age": [
				-1,
				-1
			],
			"mood": [
				-1,
				-1
			],
			"employee": [
				0,
				0.020284862196626903
			]
		},
		{
			"frame_index": 500,
			"centroid": [
				393,
				107
			],
			"gender": [
				"U",
				-1
			],
			"age": [
				-1,
				-1
			],
			"mood": [
				-1,
				-1
			],
			"employee": [
				0,
				0.016716972370559555
			]
		},
		{
			"frame_index": 501,
			"centroid": [
				394,
				107
			],
			"gender": [
				"U",
				-1
			],
			"age": [
				-1,
				-1
			],
			"mood": [
				-1,
				-1
			],
			"employee": [
				0,
				0.01835507302975865
			]
		},
		{
			"frame_index": 502,
			"centroid": [
				395,
				108
			],
			"gender": [
				"U",
				-1
			],
			"age": [
				-1,
				-1
			],
			"mood": [
				-1,
				-1
			],
			"employee": [
				0,
				0.01857852103475307
			]
		},
		{
			"frame_index": 503,
			"centroid": [
				394,
				108
			],
			"gender": [
				"U",
				-1
			],
			"age": [
				-1,
				-1
			],
			"mood": [
				-1,
				-1
			],
			"employee": [
				0,
				0.020565749235474006
			]
		},
		{
			"frame_index": 504,
			"centroid": [
				391,
				109
			],
			"gender": [
				"U",
				-1
			],
			"age": [
				-1,
				-1
			],
			"mood": [
				-1,
				-1
			],
			"employee": [
				0,
				0.026067050657214593
			]
		},
		{
			"frame_index": 505,
			"centroid": [
				390,
				110
			],
			"gender": [
				"U",
				-1
			],
			"age": [
				-1,
				-1
			],
			"mood": [
				-1,
				-1
			],
			"employee": [
				0,
				0.05751951686551775
			]
		},
		{
			"frame_index": 506,
			"centroid": [
				394,
				109
			],
			"gender": [
				"U",
				-1
			],
			"age": [
				-1,
				-1
			],
			"mood": [
				-1,
				-1
			],
			"employee": [
				0,
				0.039737108190091
			]
		},
		{
			"frame_index": 507,
			"centroid": [
				394,
				105
			],
			"gender": [
				"U",
				-1
			],
			"age": [
				-1,
				-1
			],
			"mood": [
				-1,
				-1
			],
			"employee": [
				0,
				0.02606010393914288
			]
		},
		{
			"frame_index": 508,
			"centroid": [
				393,
				105
			],
			"gender": [
				"U",
				-1
			],
			"age": [
				-1,
				-1
			],
			"mood": [
				-1,
				-1
			],
			"employee": [
				0,
				0.01962703482382032
			]
		},
		{
			"frame_index": 509,
			"centroid": [
				393,
				106
			],
			"gender": [
				"U",
				-1
			],
			"age": [
				-1,
				-1
			],
			"mood": [
				-1,
				-1
			],
			"employee": [
				0,
				0.014913455594477643
			]
		},
		{
			"frame_index": 510,
			"centroid": [
				390,
				105
			],
			"gender": [
				"U",
				-1
			],
			"age": [
				-1,
				-1
			],
			"mood": [
				-1,
				-1
			],
			"employee": [
				0,
				0.01659159159159159
			]
		},
		{
			"frame_index": 511,
			"centroid": [
				386,
				105
			],
			"gender": [
				"U",
				-1
			],
			"age": [
				-1,
				-1
			],
			"mood": [
				-1,
				-1
			],
			"employee": [
				0,
				0.018981193174741562
			]
		},
		{
			"frame_index": 512,
			"centroid": [
				385,
				105
			],
			"gender": [
				"U",
				-1
			],
			"age": [
				-1,
				-1
			],
			"mood": [
				-1,
				-1
			],
			"employee": [
				0,
				0.02076654036723987
			]
		},
		{
			"frame_index": 513,
			"centroid": [
				384,
				107
			],
			"gender": [
				"U",
				-1
			],
			"age": [
				-1,
				-1
			],
			"mood": [
				-1,
				-1
			],
			"employee": [
				0,
				0.02644890880184998
			]
		},
		{
			"frame_index": 514,
			"centroid": [
				388,
				107
			],
			"gender": [
				"U",
				-1
			],
			"age": [
				-1,
				-1
			],
			"mood": [
				-1,
				-1
			],
			"employee": [
				0,
				0.03333660403277241
			]
		},
		{
			"frame_index": 515,
			"centroid": [
				392,
				107
			],
			"gender": [
				"U",
				-1
			],
			"age": [
				-1,
				-1
			],
			"mood": [
				-1,
				-1
			],
			"employee": [
				0,
				0.03615903975993998
			]
		},
		{
			"frame_index": 516,
			"centroid": [
				394,
				106
			],
			"gender": [
				"U",
				-1
			],
			"age": [
				-1,
				-1
			],
			"mood": [
				-1,
				-1
			],
			"employee": [
				0,
				0.03386275097392868
			]
		},
		{
			"frame_index": 517,
			"centroid": [
				393,
				107
			],
			"gender": [
				"U",
				-1
			],
			"age": [
				-1,
				-1
			],
			"mood": [
				-1,
				-1
			],
			"employee": [
				0,
				0.038138138138138135
			]
		},
		{
			"frame_index": 518,
			"centroid": [
				392,
				109
			],
			"gender": [
				"U",
				-1
			],
			"age": [
				-1,
				-1
			],
			"mood": [
				-1,
				-1
			],
			"employee": [
				0,
				0.04525335775335775
			]
		},
		{
			"frame_index": 519,
			"centroid": [
				390,
				109
			],
			"gender": [
				"U",
				-1
			],
			"age": [
				-1,
				-1
			],
			"mood": [
				-1,
				-1
			],
			"employee": [
				0,
				0.03932922243946458
			]
		},
		{
			"frame_index": 520,
			"centroid": [
				389,
				109
			],
			"gender": [
				"U",
				-1
			],
			"age": [
				-1,
				-1
			],
			"mood": [
				-1,
				-1
			],
			"employee": [
				0,
				0.04139531402051052
			]
		},
		{
			"frame_index": 521,
			"centroid": [
				388,
				108
			],
			"gender": [
				"U",
				-1
			],
			"age": [
				-1,
				-1
			],
			"mood": [
				-1,
				-1
			],
			"employee": [
				0,
				0.03995617238860482
			]
		},
		{
			"frame_index": 522,
			"centroid": [
				391,
				107
			],
			"gender": [
				"U",
				-1
			],
			"age": [
				-1,
				-1
			],
			"mood": [
				-1,
				-1
			],
			"employee": [
				0,
				0.04415891301137203
			]
		},
		{
			"frame_index": 523,
			"centroid": [
				385,
				106
			],
			"gender": [
				"U",
				-1
			],
			"age": [
				-1,
				-1
			],
			"mood": [
				-1,
				-1
			],
			"employee": [
				0,
				0.04271881526485666
			]
		},
		{
			"frame_index": 524,
			"centroid": [
				389,
				107
			],
			"gender": [
				"U",
				-1
			],
			"age": [
				-1,
				-1
			],
			"mood": [
				-1,
				-1
			],
			"employee": [
				0,
				0.03798302107728337
			]
		},
		{
			"frame_index": 525,
			"centroid": [
				390,
				108
			],
			"gender": [
				"U",
				-1
			],
			"age": [
				-1,
				-1
			],
			"mood": [
				-1,
				-1
			],
			"employee": [
				0,
				0.03723776223776224
			]
		},
		{
			"frame_index": 526,
			"centroid": [
				392,
				108
			],
			"gender": [
				"U",
				-1
			],
			"age": [
				-1,
				-1
			],
			"mood": [
				-1,
				-1
			],
			"employee": [
				0,
				0.0432681529455723
			]
		},
		{
			"frame_index": 527,
			"centroid": [
				389,
				107
			],
			"gender": [
				"U",
				-1
			],
			"age": [
				-1,
				-1
			],
			"mood": [
				-1,
				-1
			],
			"employee": [
				0,
				0.042156286721504115
			]
		},
		{
			"frame_index": 528,
			"centroid": [
				391,
				108
			],
			"gender": [
				"U",
				-1
			],
			"age": [
				-1,
				-1
			],
			"mood": [
				-1,
				-1
			],
			"employee": [
				0,
				0.038461538461538464
			]
		},
		{
			"frame_index": 529,
			"centroid": [
				393,
				108
			],
			"gender": [
				"U",
				-1
			],
			"age": [
				-1,
				-1
			],
			"mood": [
				-1,
				-1
			],
			"employee": [
				0,
				0.03127596887512276
			]
		},
		{
			"frame_index": 530,
			"centroid": [
				393,
				108
			],
			"gender": [
				"U",
				-1
			],
			"age": [
				-1,
				-1
			],
			"mood": [
				-1,
				-1
			],
			"employee": [
				0,
				0.031303558826494604
			]
		},
		{
			"frame_index": 531,
			"centroid": [
				393,
				109
			],
			"gender": [
				"U",
				-1
			],
			"age": [
				-1,
				-1
			],
			"mood": [
				-1,
				-1
			],
			"employee": [
				0,
				0.03782853091608852
			]
		},
		{
			"frame_index": 532,
			"centroid": [
				393,
				110
			],
			"gender": [
				"U",
				-1
			],
			"age": [
				-1,
				-1
			],
			"mood": [
				-1,
				-1
			],
			"employee": [
				0,
				0.04434250764525994
			]
		},
		{
			"frame_index": 533,
			"centroid": [
				391,
				109
			],
			"gender": [
				"U",
				-1
			],
			"age": [
				-1,
				-1
			],
			"mood": [
				-1,
				-1
			],
			"employee": [
				0,
				0.04048170685133793
			]
		},
		{
			"frame_index": 534,
			"centroid": [
				392,
				109
			],
			"gender": [
				"U",
				-1
			],
			"age": [
				-1,
				-1
			],
			"mood": [
				-1,
				-1
			],
			"employee": [
				0,
				0.03186255960039355
			]
		},
		{
			"frame_index": 535,
			"centroid": [
				395,
				109
			],
			"gender": [
				"U",
				-1
			],
			"age": [
				-1,
				-1
			],
			"mood": [
				-1,
				-1
			],
			"employee": [
				0,
				0.03463817288702081
			]
		},
		{
			"frame_index": 536,
			"centroid": [
				393,
				109
			],
			"gender": [
				"U",
				-1
			],
			"age": [
				-1,
				-1
			],
			"mood": [
				-1,
				-1
			],
			"employee": [
				0,
				0.021917808219178082
			]
		},
		{
			"frame_index": 537,
			"centroid": [
				390,
				108
			],
			"gender": [
				"U",
				-1
			],
			"age": [
				-1,
				-1
			],
			"mood": [
				-1,
				-1
			],
			"employee": [
				0,
				0.02707432314192145
			]
		},
		{
			"frame_index": 538,
			"centroid": [
				389,
				108
			],
			"gender": [
				"U",
				-1
			],
			"age": [
				-1,
				-1
			],
			"mood": [
				-1,
				-1
			],
			"employee": [
				0,
				0.02513549798617672
			]
		},
		{
			"frame_index": 539,
			"centroid": [
				387,
				108
			],
			"gender": [
				"U",
				-1
			],
			"age": [
				-1,
				-1
			],
			"mood": [
				-1,
				-1
			],
			"employee": [
				0,
				0.027174715699305862
			]
		},
		{
			"frame_index": 540,
			"centroid": [
				385,
				108
			],
			"gender": [
				"U",
				-1
			],
			"age": [
				-1,
				-1
			],
			"mood": [
				-1,
				-1
			],
			"employee": [
				0,
				0.013231163455378702
			]
		},
		{
			"frame_index": 541,
			"centroid": [
				387,
				107
			],
			"gender": [
				"U",
				-1
			],
			"age": [
				-1,
				-1
			],
			"mood": [
				-1,
				-1
			],
			"employee": [
				0,
				0.018142451844109304
			]
		},
		{
			"frame_index": 542,
			"centroid": [
				389,
				108
			],
			"gender": [
				"U",
				-1
			],
			"age": [
				-1,
				-1
			],
			"mood": [
				-1,
				-1
			],
			"employee": [
				0,
				0.01341034655951783
			]
		},
		{
			"frame_index": 543,
			"centroid": [
				387,
				108
			],
			"gender": [
				"U",
				-1
			],
			"age": [
				-1,
				-1
			],
			"mood": [
				-1,
				-1
			],
			"employee": [
				0,
				0.017689468077199417
			]
		},
		{
			"frame_index": 544,
			"centroid": [
				389,
				108
			],
			"gender": [
				"U",
				-1
			],
			"age": [
				-1,
				-1
			],
			"mood": [
				-1,
				-1
			],
			"employee": [
				0,
				0.016797562123727176
			]
		},
		{
			"frame_index": 545,
			"centroid": [
				387,
				108
			],
			"gender": [
				"U",
				-1
			],
			"age": [
				-1,
				-1
			],
			"mood": [
				-1,
				-1
			],
			"employee": [
				0,
				0.01567405808477237
			]
		},
		{
			"frame_index": 546,
			"centroid": [
				387,
				107
			],
			"gender": [
				"U",
				-1
			],
			"age": [
				-1,
				-1
			],
			"mood": [
				-1,
				-1
			],
			"employee": [
				0,
				0.015966096683585472
			]
		},
		{
			"frame_index": 547,
			"centroid": [
				392,
				107
			],
			"gender": [
				"U",
				-1
			],
			"age": [
				-1,
				-1
			],
			"mood": [
				-1,
				-1
			],
			"employee": [
				0,
				0.014831804281345565
			]
		},
		{
			"frame_index": 548,
			"centroid": [
				392,
				107
			],
			"gender": [
				"U",
				-1
			],
			"age": [
				-1,
				-1
			],
			"mood": [
				-1,
				-1
			],
			"employee": [
				0,
				0.02098433777687668
			]
		},
		{
			"frame_index": 549,
			"centroid": [
				393,
				108
			],
			"gender": [
				"U",
				-1
			],
			"age": [
				-1,
				-1
			],
			"mood": [
				-1,
				-1
			],
			"employee": [
				0,
				0.033256880733944956
			]
		},
		{
			"frame_index": 550,
			"centroid": [
				393,
				108
			],
			"gender": [
				"U",
				-1
			],
			"age": [
				-1,
				-1
			],
			"mood": [
				-1,
				-1
			],
			"employee": [
				0,
				0.028516819571865443
			]
		},
		{
			"frame_index": 551,
			"centroid": [
				395,
				108
			],
			"gender": [
				"U",
				-1
			],
			"age": [
				-1,
				-1
			],
			"mood": [
				-1,
				-1
			],
			"employee": [
				0,
				0.03189763921427284
			]
		},
		{
			"frame_index": 552,
			"centroid": [
				396,
				108
			],
			"gender": [
				"U",
				-1
			],
			"age": [
				-1,
				-1
			],
			"mood": [
				-1,
				-1
			],
			"employee": [
				0,
				0.04655493482309125
			]
		},
		{
			"frame_index": 553,
			"centroid": [
				395,
				108
			],
			"gender": [
				"U",
				-1
			],
			"age": [
				-1,
				-1
			],
			"mood": [
				-1,
				-1
			],
			"employee": [
				0,
				0.047333932930746496
			]
		},
		{
			"frame_index": 554,
			"centroid": [
				395,
				109
			],
			"gender": [
				"U",
				-1
			],
			"age": [
				-1,
				-1
			],
			"mood": [
				-1,
				-1
			],
			"employee": [
				0,
				0.04930232558139535
			]
		},
		{
			"frame_index": 555,
			"centroid": [
				395,
				109
			],
			"gender": [
				"U",
				-1
			],
			"age": [
				-1,
				-1
			],
			"mood": [
				-1,
				-1
			],
			"employee": [
				0,
				0.04259259259259259
			]
		},
		{
			"frame_index": 556,
			"centroid": [
				394,
				109
			],
			"gender": [
				"U",
				-1
			],
			"age": [
				-1,
				-1
			],
			"mood": [
				-1,
				-1
			],
			"employee": [
				0,
				0.03433641975308642
			]
		},
		{
			"frame_index": 557,
			"centroid": [
				392,
				109
			],
			"gender": [
				"U",
				-1
			],
			"age": [
				-1,
				-1
			],
			"mood": [
				-1,
				-1
			],
			"employee": [
				0,
				0.028774776153669548
			]
		},
		{
			"frame_index": 558,
			"centroid": [
				392,
				109
			],
			"gender": [
				"U",
				-1
			],
			"age": [
				-1,
				-1
			],
			"mood": [
				-1,
				-1
			],
			"employee": [
				0,
				0.03295281582952816
			]
		},
		{
			"frame_index": 559,
			"centroid": [
				392,
				108
			],
			"gender": [
				"U",
				-1
			],
			"age": [
				-1,
				-1
			],
			"mood": [
				-1,
				-1
			],
			"employee": [
				0,
				0.030015236160487558
			]
		},
		{
			"frame_index": 560,
			"centroid": [
				394,
				109
			],
			"gender": [
				"U",
				-1
			],
			"age": [
				-1,
				-1
			],
			"mood": [
				-1,
				-1
			],
			"employee": [
				0,
				0.028291732868638203
			]
		},
		{
			"frame_index": 561,
			"centroid": [
				397,
				109
			],
			"gender": [
				"U",
				-1
			],
			"age": [
				-1,
				-1
			],
			"mood": [
				-1,
				-1
			],
			"employee": [
				0,
				0.022633529995300997
			]
		}
	]
}