{
	"json_type": "people_count",
	"branch_name": "teste",
	"host_name": "host_name",
	"mac_address_device": "dc:a6:32:6b:8e:7e",
	"mac_address_count": "0c:9d:92:8e:bf:f0",
	"video_name": "debugRasp_dca6326b8e7e_2021-02-11_14-47-44-477943",
	"width": 800,
	"height": 600,
	"person_id": 991,
	"timestamp_registered": 1613065671.6351929,
	"exits": [
		{
			"exit_name": "saida_0",
			"activity": 0,
			"param_global": {
				"name": "saida_0",
				"position": [
					[
						0.15625,
						0.485
					],
					[
						0.63125,
						0.805
					]
				],
				"exit_type": 1,
				"mask": null,
				"count": 0,
				"capacity": 0,
				"count_in": 0,
				"count_out": 0,
				"count_unknown": 0
			}
		},
		{
			"exit_name": "saida_1",
			"activity": 1,
			"param_global": {
				"name": "saida_1",
				"position": [
					[
						0.15625,
						0.49
					],
					[
						0.63125,
						0.805
					]
				],
				"exit_type": 3,
				"mask": null,
				"count": 540,
				"capacity": 0,
				"count_in": 204,
				"count_out": 204,
				"count_unknown": 0
			}
		},
		{
			"exit_name": "saida_2",
			"activity": 1,
			"param_global": {
				"name": "saida_2",
				"position": [
					[
						0.15625,
						0.495
					],
					[
						0.63125,
						0.805
					]
				],
				"exit_type": 3,
				"mask": null,
				"count": 537,
				"capacity": -2,
				"count_in": 204,
				"count_out": 205,
				"count_unknown": 0
			}
		},
		{
			"exit_name": "saida_3",
			"activity": 1,
			"param_global": {
				"name": "saida_3",
				"position": [
					[
						0.15625,
						0.5
					],
					[
						0.63125,
						0.805
					]
				],
				"exit_type": 3,
				"mask": null,
				"count": 536,
				"capacity": -2,
				"count_in": 205,
				"count_out": 206,
				"count_unknown": 0
			}
		},
		{
			"exit_name": "saida_4",
			"activity": 1,
			"param_global": {
				"name": "saida_4",
				"position": [
					[
						0.15625,
						0.505
					],
					[
						0.63125,
						0.805
					]
				],
				"exit_type": 3,
				"mask": null,
				"count": 534,
				"capacity": -4,
				"count_in": 204,
				"count_out": 206,
				"count_unknown": 0
			}
		},
		{
			"exit_name": "saida_5",
			"activity": 1,
			"param_global": {
				"name": "saida_5",
				"position": [
					[
						0.15625,
						0.51
					],
					[
						0.63125,
						0.805
					]
				],
				"exit_type": 3,
				"mask": null,
				"count": 530,
				"capacity": -2,
				"count_in": 204,
				"count_out": 205,
				"count_unknown": 0
			}
		},
		{
			"exit_name": "saida_6",
			"activity": 1,
			"param_global": {
				"name": "saida_6",
				"position": [
					[
						0.15625,
						0.515
					],
					[
						0.63125,
						0.805
					]
				],
				"exit_type": 3,
				"mask": null,
				"count": 528,
				"capacity": -6,
				"count_in": 203,
				"count_out": 206,
				"count_unknown": 0
			}
		},
		{
			"exit_name": "saida_7",
			"activity": 1,
			"param_global": {
				"name": "saida_7",
				"position": [
					[
						0.15625,
						0.52
					],
					[
						0.63125,
						0.805
					]
				],
				"exit_type": 3,
				"mask": null,
				"count": 527,
				"capacity": -2,
				"count_in": 204,
				"count_out": 205,
				"count_unknown": 0
			}
		},
		{
			"exit_name": "saida_8",
			"activity": 1,
			"param_global": {
				"name": "saida_8",
				"position": [
					[
						0.15625,
						0.525
					],
					[
						0.63125,
						0.805
					]
				],
				"exit_type": 3,
				"mask": null,
				"count": 527,
				"capacity": -6,
				"count_in": 203,
				"count_out": 206,
				"count_unknown": 0
			}
		},
		{
			"exit_name": "saida_9",
			"activity": 1,
			"param_global": {
				"name": "saida_9",
				"position": [
					[
						0.15625,
						0.53
					],
					[
						0.63125,
						0.805
					]
				],
				"exit_type": 3,
				"mask": null,
				"count": 524,
				"capacity": -6,
				"count_in": 204,
				"count_out": 207,
				"count_unknown": 0
			}
		},
		{
			"exit_name": "saida_10",
			"activity": 1,
			"param_global": {
				"name": "saida_10",
				"position": [
					[
						0.15625,
						0.535
					],
					[
						0.63125,
						0.805
					]
				],
				"exit_type": 3,
				"mask": null,
				"count": 523,
				"capacity": 0,
				"count_in": 205,
				"count_out": 205,
				"count_unknown": 0
			}
		},
		{
			"exit_name": "saida_11",
			"activity": 1,
			"param_global": {
				"name": "saida_11",
				"position": [
					[
						0.15625,
						0.54
					],
					[
						0.63125,
						0.805
					]
				],
				"exit_type": 3,
				"mask": null,
				"count": 518,
				"capacity": 2,
				"count_in": 206,
				"count_out": 205,
				"count_unknown": 0
			}
		},
		{
			"exit_name": "saida_12",
			"activity": 1,
			"param_global": {
				"name": "saida_12",
				"position": [
					[
						0.15625,
						0.545
					],
					[
						0.63125,
						0.805
					]
				],
				"exit_type": 3,
				"mask": null,
				"count": 515,
				"capacity": 4,
				"count_in": 207,
				"count_out": 205,
				"count_unknown": 0
			}
		},
		{
			"exit_name": "saida_13",
			"activity": 1,
			"param_global": {
				"name": "saida_13",
				"position": [
					[
						0.15625,
						0.55
					],
					[
						0.63125,
						0.805
					]
				],
				"exit_type": 3,
				"mask": null,
				"count": 514,
				"capacity": 6,
				"count_in": 207,
				"count_out": 204,
				"count_unknown": 0
			}
		},
		{
			"exit_name": "saida_14",
			"activity": 1,
			"param_global": {
				"name": "saida_14",
				"position": [
					[
						0.15625,
						0.555
					],
					[
						0.63125,
						0.805
					]
				],
				"exit_type": 3,
				"mask": null,
				"count": 512,
				"capacity": 2,
				"count_in": 207,
				"count_out": 206,
				"count_unknown": 0
			}
		},
		{
			"exit_name": "saida_15",
			"activity": 1,
			"param_global": {
				"name": "saida_15",
				"position": [
					[
						0.15625,
						0.56
					],
					[
						0.63125,
						0.805
					]
				],
				"exit_type": 3,
				"mask": null,
				"count": 510,
				"capacity": -2,
				"count_in": 205,
				"count_out": 206,
				"count_unknown": 0
			}
		},
		{
			"exit_name": "saida_16",
			"activity": 1,
			"param_global": {
				"name": "saida_16",
				"position": [
					[
						0.15625,
						0.5650000000000001
					],
					[
						0.63125,
						0.805
					]
				],
				"exit_type": 3,
				"mask": null,
				"count": 508,
				"capacity": 6,
				"count_in": 207,
				"count_out": 204,
				"count_unknown": 0
			}
		},
		{
			"exit_name": "saida_17",
			"activity": 1,
			"param_global": {
				"name": "saida_17",
				"position": [
					[
						0.15625,
						0.5700000000000001
					],
					[
						0.63125,
						0.805
					]
				],
				"exit_type": 3,
				"mask": null,
				"count": 508,
				"capacity": 4,
				"count_in": 206,
				"count_out": 204,
				"count_unknown": 0
			}
		},
		{
			"exit_name": "saida_18",
			"activity": 1,
			"param_global": {
				"name": "saida_18",
				"position": [
					[
						0.15625,
						0.5750000000000001
					],
					[
						0.63125,
						0.805
					]
				],
				"exit_type": 3,
				"mask": null,
				"count": 507,
				"capacity": 4,
				"count_in": 206,
				"count_out": 204,
				"count_unknown": 0
			}
		},
		{
			"exit_name": "saida_19",
			"activity": 1,
			"param_global": {
				"name": "saida_19",
				"position": [
					[
						0.15625,
						0.5800000000000001
					],
					[
						0.63125,
						0.805
					]
				],
				"exit_type": 3,
				"mask": null,
				"count": 506,
				"capacity": 6,
				"count_in": 206,
				"count_out": 203,
				"count_unknown": 0
			}
		},
		{
			"exit_name": "saida_20",
			"activity": 1,
			"param_global": {
				"name": "saida_20",
				"position": [
					[
						0.15625,
						0.5850000000000001
					],
					[
						0.63125,
						0.805
					]
				],
				"exit_type": 3,
				"mask": null,
				"count": 506,
				"capacity": 6,
				"count_in": 206,
				"count_out": 203,
				"count_unknown": 0
			}
		},
		{
			"exit_name": "saida_21",
			"activity": 1,
			"param_global": {
				"name": "saida_21",
				"position": [
					[
						0.15625,
						0.5900000000000001
					],
					[
						0.63125,
						0.805
					]
				],
				"exit_type": 3,
				"mask": null,
				"count": 506,
				"capacity": 0,
				"count_in": 206,
				"count_out": 206,
				"count_unknown": 0
			}
		},
		{
			"exit_name": "saida_22",
			"activity": 1,
			"param_global": {
				"name": "saida_22",
				"position": [
					[
						0.15625,
						0.5950000000000001
					],
					[
						0.63125,
						0.805
					]
				],
				"exit_type": 3,
				"mask": null,
				"count": 505,
				"capacity": -2,
				"count_in": 205,
				"count_out": 206,
				"count_unknown": 0
			}
		},
		{
			"exit_name": "saida_23",
			"activity": 1,
			"param_global": {
				"name": "saida_23",
				"position": [
					[
						0.15625,
						0.6000000000000001
					],
					[
						0.63125,
						0.805
					]
				],
				"exit_type": 3,
				"mask": null,
				"count": 505,
				"capacity": -2,
				"count_in": 204,
				"count_out": 205,
				"count_unknown": 0
			}
		},
		{
			"exit_name": "saida_24",
			"activity": 1,
			"param_global": {
				"name": "saida_24",
				"position": [
					[
						0.15625,
						0.6050000000000001
					],
					[
						0.63125,
						0.805
					]
				],
				"exit_type": 3,
				"mask": null,
				"count": 505,
				"capacity": -4,
				"count_in": 204,
				"count_out": 206,
				"count_unknown": 0
			}
		},
		{
			"exit_name": "saida_25",
			"activity": 1,
			"param_global": {
				"name": "saida_25",
				"position": [
					[
						0.15625,
						0.6100000000000001
					],
					[
						0.63125,
						0.805
					]
				],
				"exit_type": 3,
				"mask": null,
				"count": 503,
				"capacity": 0,
				"count_in": 205,
				"count_out": 205,
				"count_unknown": 0
			}
		},
		{
			"exit_name": "saida_26",
			"activity": 1,
			"param_global": {
				"name": "saida_26",
				"position": [
					[
						0.15625,
						0.6150000000000001
					],
					[
						0.63125,
						0.805
					]
				],
				"exit_type": 3,
				"mask": null,
				"count": 502,
				"capacity": 2,
				"count_in": 206,
				"count_out": 205,
				"count_unknown": 1
			}
		},
		{
			"exit_name": "saida_27",
			"activity": 1,
			"param_global": {
				"name": "saida_27",
				"position": [
					[
						0.15625,
						0.6200000000000001
					],
					[
						0.63125,
						0.805
					]
				],
				"exit_type": 3,
				"mask": null,
				"count": 501,
				"capacity": 0,
				"count_in": 206,
				"count_out": 206,
				"count_unknown": 0
			}
		},
		{
			"exit_name": "saida_28",
			"activity": 1,
			"param_global": {
				"name": "saida_28",
				"position": [
					[
						0.15625,
						0.6250000000000001
					],
					[
						0.63125,
						0.805
					]
				],
				"exit_type": 3,
				"mask": null,
				"count": 501,
				"capacity": 2,
				"count_in": 206,
				"count_out": 205,
				"count_unknown": 0
			}
		},
		{
			"exit_name": "saida_29",
			"activity": 1,
			"param_global": {
				"name": "saida_29",
				"position": [
					[
						0.15625,
						0.6300000000000001
					],
					[
						0.63125,
						0.805
					]
				],
				"exit_type": 3,
				"mask": null,
				"count": 501,
				"capacity": 4,
				"count_in": 207,
				"count_out": 205,
				"count_unknown": 0
			}
		},
		{
			"exit_name": "saida_30",
			"activity": 1,
			"param_global": {
				"name": "saida_30",
				"position": [
					[
						0.15625,
						0.6350000000000001
					],
					[
						0.63125,
						0.805
					]
				],
				"exit_type": 3,
				"mask": null,
				"count": 500,
				"capacity": 0,
				"count_in": 205,
				"count_out": 205,
				"count_unknown": 0
			}
		},
		{
			"exit_name": "saida_31",
			"activity": 1,
			"param_global": {
				"name": "saida_31",
				"position": [
					[
						0.15625,
						0.6400000000000001
					],
					[
						0.63125,
						0.805
					]
				],
				"exit_type": 3,
				"mask": null,
				"count": 500,
				"capacity": 4,
				"count_in": 205,
				"count_out": 203,
				"count_unknown": 0
			}
		},
		{
			"exit_name": "saida_32",
			"activity": 1,
			"param_global": {
				"name": "saida_32",
				"position": [
					[
						0.15625,
						0.6450000000000001
					],
					[
						0.63125,
						0.805
					]
				],
				"exit_type": 3,
				"mask": null,
				"count": 499,
				"capacity": 6,
				"count_in": 206,
				"count_out": 203,
				"count_unknown": 0
			}
		},
		{
			"exit_name": "saida_33",
			"activity": 1,
			"param_global": {
				"name": "saida_33",
				"position": [
					[
						0.15625,
						0.6500000000000001
					],
					[
						0.63125,
						0.805
					]
				],
				"exit_type": 3,
				"mask": null,
				"count": 498,
				"capacity": 4,
				"count_in": 205,
				"count_out": 203,
				"count_unknown": 0
			}
		},
		{
			"exit_name": "saida_34",
			"activity": 1,
			"param_global": {
				"name": "saida_34",
				"position": [
					[
						0.15625,
						0.6550000000000001
					],
					[
						0.63125,
						0.805
					]
				],
				"exit_type": 3,
				"mask": null,
				"count": 498,
				"capacity": 0,
				"count_in": 203,
				"count_out": 203,
				"count_unknown": 0
			}
		},
		{
			"exit_name": "saida_35",
			"activity": 1,
			"param_global": {
				"name": "saida_35",
				"position": [
					[
						0.15625,
						0.6600000000000001
					],
					[
						0.63125,
						0.805
					]
				],
				"exit_type": 3,
				"mask": null,
				"count": 497,
				"capacity": -2,
				"count_in": 202,
				"count_out": 203,
				"count_unknown": 0
			}
		},
		{
			"exit_name": "saida_36",
			"activity": 1,
			"param_global": {
				"name": "saida_36",
				"position": [
					[
						0.15625,
						0.6650000000000001
					],
					[
						0.63125,
						0.805
					]
				],
				"exit_type": 3,
				"mask": null,
				"count": 497,
				"capacity": 0,
				"count_in": 202,
				"count_out": 202,
				"count_unknown": 0
			}
		},
		{
			"exit_name": "saida_37",
			"activity": 1,
			"param_global": {
				"name": "saida_37",
				"position": [
					[
						0.15625,
						0.6700000000000002
					],
					[
						0.63125,
						0.805
					]
				],
				"exit_type": 3,
				"mask": null,
				"count": 495,
				"capacity": 4,
				"count_in": 202,
				"count_out": 200,
				"count_unknown": 0
			}
		},
		{
			"exit_name": "saida_38",
			"activity": 1,
			"param_global": {
				"name": "saida_38",
				"position": [
					[
						0.15625,
						0.6750000000000002
					],
					[
						0.63125,
						0.805
					]
				],
				"exit_type": 3,
				"mask": null,
				"count": 495,
				"capacity": 2,
				"count_in": 199,
				"count_out": 198,
				"count_unknown": 0
			}
		},
		{
			"exit_name": "saida_39",
			"activity": 1,
			"param_global": {
				"name": "saida_39",
				"position": [
					[
						0.15625,
						0.6800000000000002
					],
					[
						0.63125,
						0.805
					]
				],
				"exit_type": 3,
				"mask": null,
				"count": 495,
				"capacity": 12,
				"count_in": 198,
				"count_out": 192,
				"count_unknown": 0
			}
		}
	],
	"detected_object": [
		{
			"frame_index": 34,
			"centroid": [
				144,
				552
			],
			"gender": [
				"U",
				-1
			],
			"age": [
				-1,
				-1
			],
			"mood": [
				-1,
				-1
			],
			"employee": [
				0,
				0.012013536379018613
			]
		},
		{
			"frame_index": 35,
			"centroid": [
				147,
				549
			],
			"gender": [
				"U",
				-1
			],
			"age": [
				-1,
				-1
			],
			"mood": [
				-1,
				-1
			],
			"employee": [
				0,
				0.006715951686797168
			]
		},
		{
			"frame_index": 36,
			"centroid": [
				169,
				531
			],
			"gender": [
				"U",
				-1
			],
			"age": [
				-1,
				-1
			],
			"mood": [
				-1,
				-1
			],
			"employee": [
				0,
				0.005427057759400439
			]
		},
		{
			"frame_index": 37,
			"centroid": [
				182,
				522
			],
			"gender": [
				"U",
				-1
			],
			"age": [
				-1,
				-1
			],
			"mood": [
				-1,
				-1
			],
			"employee": [
				0,
				0.005005735738867452
			]
		},
		{
			"frame_index": 38,
			"centroid": [
				191,
				509
			],
			"gender": [
				"U",
				-1
			],
			"age": [
				-1,
				-1
			],
			"mood": [
				-1,
				-1
			],
			"employee": [
				0,
				0.007760532150776054
			]
		},
		{
			"frame_index": 39,
			"centroid": [
				196,
				503
			],
			"gender": [
				"U",
				-1
			],
			"age": [
				-1,
				-1
			],
			"mood": [
				-1,
				-1
			],
			"employee": [
				0,
				0.009437182988685134
			]
		},
		{
			"frame_index": 40,
			"centroid": [
				201,
				498
			],
			"gender": [
				"U",
				-1
			],
			"age": [
				-1,
				-1
			],
			"mood": [
				-1,
				-1
			],
			"employee": [
				0,
				0.010921165908252367
			]
		},
		{
			"frame_index": 41,
			"centroid": [
				202,
				485
			],
			"gender": [
				"U",
				-1
			],
			"age": [
				-1,
				-1
			],
			"mood": [
				-1,
				-1
			],
			"employee": [
				0,
				0.01131379381020701
			]
		},
		{
			"frame_index": 42,
			"centroid": [
				204,
				486
			],
			"gender": [
				"U",
				-1
			],
			"age": [
				-1,
				-1
			],
			"mood": [
				-1,
				-1
			],
			"employee": [
				0,
				0.012357884330202669
			]
		},
		{
			"frame_index": 43,
			"centroid": [
				204,
				483
			],
			"gender": [
				"U",
				-1
			],
			"age": [
				-1,
				-1
			],
			"mood": [
				-1,
				-1
			],
			"employee": [
				0,
				0.025323841755163962
			]
		},
		{
			"frame_index": 44,
			"centroid": [
				212,
				468
			],
			"gender": [
				"U",
				-1
			],
			"age": [
				-1,
				-1
			],
			"mood": [
				-1,
				-1
			],
			"employee": [
				0,
				0.017828900071890728
			]
		},
		{
			"frame_index": 45,
			"centroid": [
				217,
				462
			],
			"gender": [
				"U",
				-1
			],
			"age": [
				-1,
				-1
			],
			"mood": [
				-1,
				-1
			],
			"employee": [
				0,
				0.035083462732919256
			]
		},
		{
			"frame_index": 46,
			"centroid": [
				225,
				456
			],
			"gender": [
				"U",
				-1
			],
			"age": [
				-1,
				-1
			],
			"mood": [
				-1,
				-1
			],
			"employee": [
				0,
				0.05593220338983051
			]
		},
		{
			"frame_index": 47,
			"centroid": [
				238,
				446
			],
			"gender": [
				"U",
				-1
			],
			"age": [
				-1,
				-1
			],
			"mood": [
				-1,
				-1
			],
			"employee": [
				0,
				0.04481591197630131
			]
		},
		{
			"frame_index": 48,
			"centroid": [
				249,
				425
			],
			"gender": [
				"U",
				-1
			],
			"age": [
				-1,
				-1
			],
			"mood": [
				-1,
				-1
			],
			"employee": [
				0,
				0.04376094865921035
			]
		},
		{
			"frame_index": 49,
			"centroid": [
				252,
				406
			],
			"gender": [
				"U",
				-1
			],
			"age": [
				-1,
				-1
			],
			"mood": [
				-1,
				-1
			],
			"employee": [
				0,
				0.0425561797752809
			]
		},
		{
			"frame_index": 50,
			"centroid": [
				253,
				390
			],
			"gender": [
				"U",
				-1
			],
			"age": [
				-1,
				-1
			],
			"mood": [
				-1,
				-1
			],
			"employee": [
				0,
				0.04772876892692561
			]
		},
		{
			"frame_index": 51,
			"centroid": [
				255,
				387
			],
			"gender": [
				"U",
				-1
			],
			"age": [
				-1,
				-1
			],
			"mood": [
				-1,
				-1
			],
			"employee": [
				0,
				0.05193877551020408
			]
		},
		{
			"frame_index": 52,
			"centroid": [
				253,
				390
			],
			"gender": [
				"U",
				-1
			],
			"age": [
				-1,
				-1
			],
			"mood": [
				-1,
				-1
			],
			"employee": [
				0,
				0.061769005847953216
			]
		},
		{
			"frame_index": 53,
			"centroid": [
				258,
				386
			],
			"gender": [
				"U",
				-1
			],
			"age": [
				-1,
				-1
			],
			"mood": [
				-1,
				-1
			],
			"employee": [
				0,
				0.09180282470229853
			]
		},
		{
			"frame_index": 54,
			"centroid": [
				259,
				366
			],
			"gender": [
				"U",
				-1
			],
			"age": [
				-1,
				-1
			],
			"mood": [
				-1,
				-1
			],
			"employee": [
				0,
				0.09498069498069497
			]
		},
		{
			"frame_index": 55,
			"centroid": [
				263,
				356
			],
			"gender": [
				"U",
				-1
			],
			"age": [
				-1,
				-1
			],
			"mood": [
				-1,
				-1
			],
			"employee": [
				0,
				0.09754479097544791
			]
		},
		{
			"frame_index": 56,
			"centroid": [
				270,
				343
			],
			"gender": [
				"U",
				-1
			],
			"age": [
				-1,
				-1
			],
			"mood": [
				-1,
				-1
			],
			"employee": [
				0,
				0.08449275362318841
			]
		},
		{
			"frame_index": 57,
			"centroid": [
				276,
				335
			],
			"gender": [
				"U",
				-1
			],
			"age": [
				-1,
				-1
			],
			"mood": [
				-1,
				-1
			],
			"employee": [
				0,
				0.07634654471544715
			]
		},
		{
			"frame_index": 58,
			"centroid": [
				287,
				329
			],
			"gender": [
				"U",
				-1
			],
			"age": [
				-1,
				-1
			],
			"mood": [
				-1,
				-1
			],
			"employee": [
				0,
				0.07250830564784053
			]
		},
		{
			"frame_index": 59,
			"centroid": [
				306,
				323
			],
			"gender": [
				"U",
				-1
			],
			"age": [
				-1,
				-1
			],
			"mood": [
				-1,
				-1
			],
			"employee": [
				0,
				0.05701893578758066
			]
		},
		{
			"frame_index": 60,
			"centroid": [
				313,
				313
			],
			"gender": [
				"U",
				-1
			],
			"age": [
				-1,
				-1
			],
			"mood": [
				-1,
				-1
			],
			"employee": [
				0,
				0.060747288067496984
			]
		},
		{
			"frame_index": 61,
			"centroid": [
				315,
				306
			],
			"gender": [
				"U",
				-1
			],
			"age": [
				-1,
				-1
			],
			"mood": [
				-1,
				-1
			],
			"employee": [
				0,
				0.060374220374220376
			]
		},
		{
			"frame_index": 62,
			"centroid": [
				327,
				297
			],
			"gender": [
				"U",
				-1
			],
			"age": [
				-1,
				-1
			],
			"mood": [
				-1,
				-1
			],
			"employee": [
				0,
				0.05606312292358804
			]
		},
		{
			"frame_index": 63,
			"centroid": [
				330,
				289
			],
			"gender": [
				"U",
				-1
			],
			"age": [
				-1,
				-1
			],
			"mood": [
				-1,
				-1
			],
			"employee": [
				0,
				0.04829136690647482
			]
		},
		{
			"frame_index": 64,
			"centroid": [
				343,
				281
			],
			"gender": [
				"U",
				-1
			],
			"age": [
				-1,
				-1
			],
			"mood": [
				-1,
				-1
			],
			"employee": [
				0,
				0.061238988348962776
			]
		},
		{
			"frame_index": 65,
			"centroid": [
				348,
				277
			],
			"gender": [
				"U",
				-1
			],
			"age": [
				-1,
				-1
			],
			"mood": [
				-1,
				-1
			],
			"employee": [
				0,
				0.045786726323639074
			]
		},
		{
			"frame_index": 66,
			"centroid": [
				354,
				272
			],
			"gender": [
				"U",
				-1
			],
			"age": [
				-1,
				-1
			],
			"mood": [
				-1,
				-1
			],
			"employee": [
				0,
				0.03865671641791045
			]
		},
		{
			"frame_index": 67,
			"centroid": [
				365,
				268
			],
			"gender": [
				"U",
				-1
			],
			"age": [
				-1,
				-1
			],
			"mood": [
				-1,
				-1
			],
			"employee": [
				0,
				0.07472776769509983
			]
		},
		{
			"frame_index": 68,
			"centroid": [
				377,
				259
			],
			"gender": [
				"U",
				-1
			],
			"age": [
				-1,
				-1
			],
			"mood": [
				-1,
				-1
			],
			"employee": [
				0,
				0.05543127019637087
			]
		},
		{
			"frame_index": 69,
			"centroid": [
				389,
				247
			],
			"gender": [
				"U",
				-1
			],
			"age": [
				-1,
				-1
			],
			"mood": [
				-1,
				-1
			],
			"employee": [
				0,
				0.07597737890336857
			]
		},
		{
			"frame_index": 70,
			"centroid": [
				404,
				242
			],
			"gender": [
				"U",
				-1
			],
			"age": [
				-1,
				-1
			],
			"mood": [
				-1,
				-1
			],
			"employee": [
				0,
				0.03879692580549808
			]
		},
		{
			"frame_index": 71,
			"centroid": [
				423,
				241
			],
			"gender": [
				"U",
				-1
			],
			"age": [
				-1,
				-1
			],
			"mood": [
				-1,
				-1
			],
			"employee": [
				0,
				0.04232150875617423
			]
		},
		{
			"frame_index": 72,
			"centroid": [
				436,
				241
			],
			"gender": [
				"U",
				-1
			],
			"age": [
				-1,
				-1
			],
			"mood": [
				-1,
				-1
			],
			"employee": [
				0,
				0.03253944174757282
			]
		},
		{
			"frame_index": 73,
			"centroid": [
				444,
				234
			],
			"gender": [
				"U",
				-1
			],
			"age": [
				-1,
				-1
			],
			"mood": [
				-1,
				-1
			],
			"employee": [
				0,
				0.0365427135678392
			]
		},
		{
			"frame_index": 74,
			"centroid": [
				458,
				222
			],
			"gender": [
				"U",
				-1
			],
			"age": [
				-1,
				-1
			],
			"mood": [
				-1,
				-1
			],
			"employee": [
				0,
				0.039388618405299704
			]
		},
		{
			"frame_index": 75,
			"centroid": [
				464,
				214
			],
			"gender": [
				"U",
				-1
			],
			"age": [
				-1,
				-1
			],
			"mood": [
				-1,
				-1
			],
			"employee": [
				0,
				0.037220528455284556
			]
		},
		{
			"frame_index": 76,
			"centroid": [
				473,
				205
			],
			"gender": [
				"U",
				-1
			],
			"age": [
				-1,
				-1
			],
			"mood": [
				-1,
				-1
			],
			"employee": [
				0,
				0.03422253422253422
			]
		},
		{
			"frame_index": 77,
			"centroid": [
				483,
				203
			],
			"gender": [
				"U",
				-1
			],
			"age": [
				-1,
				-1
			],
			"mood": [
				-1,
				-1
			],
			"employee": [
				0,
				0.02748201438848921
			]
		},
		{
			"frame_index": 78,
			"centroid": [
				493,
				200
			],
			"gender": [
				"U",
				-1
			],
			"age": [
				-1,
				-1
			],
			"mood": [
				-1,
				-1
			],
			"employee": [
				0,
				0.03718891402714932
			]
		},
		{
			"frame_index": 79,
			"centroid": [
				502,
				196
			],
			"gender": [
				"U",
				-1
			],
			"age": [
				-1,
				-1
			],
			"mood": [
				-1,
				-1
			],
			"employee": [
				0,
				0.014537231465029882
			]
		},
		{
			"frame_index": 80,
			"centroid": [
				514,
				190
			],
			"gender": [
				"U",
				-1
			],
			"age": [
				-1,
				-1
			],
			"mood": [
				-1,
				-1
			],
			"employee": [
				0,
				0.009828571428571428
			]
		},
		{
			"frame_index": 81,
			"centroid": [
				529,
				188
			],
			"gender": [
				"U",
				-1
			],
			"age": [
				-1,
				-1
			],
			"mood": [
				-1,
				-1
			],
			"employee": [
				0,
				0.013141025641025641
			]
		},
		{
			"frame_index": 82,
			"centroid": [
				547,
				184
			],
			"gender": [
				"U",
				-1
			],
			"age": [
				-1,
				-1
			],
			"mood": [
				-1,
				-1
			],
			"employee": [
				0,
				0.0097771236333053
			]
		},
		{
			"frame_index": 83,
			"centroid": [
				563,
				191
			],
			"gender": [
				"U",
				-1
			],
			"age": [
				-1,
				-1
			],
			"mood": [
				-1,
				-1
			],
			"employee": [
				0,
				0.01063321385902031
			]
		},
		{
			"frame_index": 84,
			"centroid": [
				564,
				183
			],
			"gender": [
				"U",
				-1
			],
			"age": [
				-1,
				-1
			],
			"mood": [
				-1,
				-1
			],
			"employee": [
				0,
				0.012155330058445983
			]
		},
		{
			"frame_index": 85,
			"centroid": [
				577,
				174
			],
			"gender": [
				"U",
				-1
			],
			"age": [
				-1,
				-1
			],
			"mood": [
				-1,
				-1
			],
			"employee": [
				0,
				0.006260262725779967
			]
		},
		{
			"frame_index": 86,
			"centroid": [
				586,
				173
			],
			"gender": [
				"U",
				-1
			],
			"age": [
				-1,
				-1
			],
			"mood": [
				-1,
				-1
			],
			"employee": [
				0,
				0.008471760797342192
			]
		},
		{
			"frame_index": 87,
			"centroid": [
				601,
				172
			],
			"gender": [
				"U",
				-1
			],
			"age": [
				-1,
				-1
			],
			"mood": [
				-1,
				-1
			],
			"employee": [
				0,
				0.030616509926854753
			]
		},
		{
			"frame_index": 88,
			"centroid": [
				617,
				169
			],
			"gender": [
				"U",
				-1
			],
			"age": [
				-1,
				-1
			],
			"mood": [
				-1,
				-1
			],
			"employee": [
				0,
				0.012610976594027441
			]
		},
		{
			"frame_index": 89,
			"centroid": [
				636,
				169
			],
			"gender": [
				"U",
				-1
			],
			"age": [
				-1,
				-1
			],
			"mood": [
				-1,
				-1
			],
			"employee": [
				0,
				0.010107816711590296
			]
		},
		{
			"frame_index": 90,
			"centroid": [
				653,
				162
			],
			"gender": [
				"U",
				-1
			],
			"age": [
				-1,
				-1
			],
			"mood": [
				-1,
				-1
			],
			"employee": [
				0,
				0.020309372156505915
			]
		},
		{
			"frame_index": 91,
			"centroid": [
				670,
				160
			],
			"gender": [
				"U",
				-1
			],
			"age": [
				-1,
				-1
			],
			"mood": [
				-1,
				-1
			],
			"employee": [
				0,
				0.012363850456284957
			]
		},
		{
			"frame_index": 92,
			"centroid": [
				682,
				154
			],
			"gender": [
				"U",
				-1
			],
			"age": [
				-1,
				-1
			],
			"mood": [
				-1,
				-1
			],
			"employee": [
				0,
				0.012943432406519654
			]
		},
		{
			"frame_index": 93,
			"centroid": [
				689,
				154
			],
			"gender": [
				"U",
				-1
			],
			"age": [
				-1,
				-1
			],
			"mood": [
				-1,
				-1
			],
			"employee": [
				0,
				0.014739751266697375
			]
		},
		{
			"frame_index": 94,
			"centroid": [
				691,
				154
			],
			"gender": [
				"U",
				-1
			],
			"age": [
				-1,
				-1
			],
			"mood": [
				-1,
				-1
			],
			"employee": [
				0,
				0.00035622402533148624
			]
		},
		{
			"frame_index": 95,
			"centroid": [
				692,
				126
			],
			"gender": [
				"U",
				-1
			],
			"age": [
				-1,
				-1
			],
			"mood": [
				-1,
				-1
			],
			"employee": [
				0,
				0.00040048057669203043
			]
		},
		{
			"frame_index": 96,
			"centroid": [
				712,
				141
			],
			"gender": [
				"U",
				-1
			],
			"age": [
				-1,
				-1
			],
			"mood": [
				-1,
				-1
			],
			"employee": [
				0,
				0.004177801196883586
			]
		},
		{
			"frame_index": 97,
			"centroid": [
				700,
				118
			],
			"gender": [
				"U",
				-1
			],
			"age": [
				-1,
				-1
			],
			"mood": [
				-1,
				-1
			],
			"employee": [
				0,
				0.010714285714285714
			]
		},
		{
			"frame_index": 99,
			"centroid": [
				729,
				145
			],
			"gender": [
				"U",
				-1
			],
			"age": [
				-1,
				-1
			],
			"mood": [
				-1,
				-1
			],
			"employee": [
				0,
				0.014448761534725595
			]
		},
		{
			"frame_index": 100,
			"centroid": [
				733,
				137
			],
			"gender": [
				"U",
				-1
			],
			"age": [
				-1,
				-1
			],
			"mood": [
				-1,
				-1
			],
			"employee": [
				0,
				0.009234178773701059
			]
		},
		{
			"frame_index": 101,
			"centroid": [
				741,
				132
			],
			"gender": [
				"U",
				-1
			],
			"age": [
				-1,
				-1
			],
			"mood": [
				-1,
				-1
			],
			"employee": [
				0,
				0.0011401545542840251
			]
		},
		{
			"frame_index": 102,
			"centroid": [
				743,
				116
			],
			"gender": [
				"U",
				-1
			],
			"age": [
				-1,
				-1
			],
			"mood": [
				-1,
				-1
			],
			"employee": [
				0,
				0.0
			]
		},
		{
			"frame_index": 103,
			"centroid": [
				742,
				110
			],
			"gender": [
				"U",
				-1
			],
			"age": [
				-1,
				-1
			],
			"mood": [
				-1,
				-1
			],
			"employee": [
				0,
				0.0
			]
		},
		{
			"frame_index": 104,
			"centroid": [
				743,
				151
			],
			"gender": [
				"U",
				-1
			],
			"age": [
				-1,
				-1
			],
			"mood": [
				-1,
				-1
			],
			"employee": [
				0,
				0.0
			]
		}
	]
}